Workbook

Sheet ahri nyoret nyoret bntr 💰BUDGE
B1: =CONCATENATE('🏦COVER🏦'!D7," 💰Budget Plan💰") -> #REF!
B2: 💔Pessimistic Plan💔 | G2: 🤍Realistic Plan🤍 | L2: 💗Optimistic Plan💗
B3: REVENUE BREAKDOWN | G3: REVENUE BREAKDOWN | L3: REVENUE BREAKDOWN
B4: (revenue stream) | C4: P | D4: Q | E4: Total | G4: (revenue stream) | H4: P | I4: Q | J4: Total | L4: (revenue stream) | M4: P | N4: Q | O4: Total
B5: Delegates Fee | C5: 1150000 | D5: 320 | E5: =C5*D5 -> 368000000 | G5: Delegates Fee | H5: 1150000 | I5: 320 | J5: =H5*I5 -> 368000000 | L5: Delegates Fee | M5: 1150000 | N5: 320 | O5: =M5*N5 -> 368000000
B6: Commitment Fee | C6: 50000 | D6: 320 | E6: =C6*D6 -> 16000000 | G6: Commitment Fee | H6: 50000 | I6: 320 | J6: =H6*I6 -> 16000000 | L6: Commitment Fee | M6: 50000 | N6: 320 | O6: =M6*N6 -> 16000000
B7: Working Capital from MC | C7: 40000000 | D7: 1 | E7: =C7*D7 -> 40000000 | G7: Working Capital from MC | H7: 40000000 | I7: 1 | J7: =H7*I7 -> 40000000 | L7: Working Capital from MC | M7: 40000000 | N7: 1 | O7: =M7*N7 -> 40000000
B8: Working Capital from LC | C8: 5000000 | D8: 1 | E8: =C8*D8 -> 5000000 | G8: Working Capital from LC | H8: 5000000 | I8: 1 | J8: =H8*I8 -> 5000000 | L8: Working Capital from LC | M8: 5000000 | N8: 1 | O8: =M8*N8 -> 5000000
B9: [Merchandise] Baseball Cap | C9: 65000 | D9: 5 | E9: =C9*D9 -> 325000 | G9: [Merchandise] Baseball Cap | H9: 65000 | I9: 10 | J9: =H9*I9 -> 650000 | L9: [Merchandise] Baseball Cap | M9: 65000 | N9: 15 | O9: =M9*N9 -> 975000
B10: [Merchandise] Baseball Shirt | C10: 165000 | D10: 5 | E10: =C10*D10 -> 825000 | G10: [Merchandise] Baseball Shirt | H10: 165000 | I10: 10 | J10: =H10*I10 -> 1650000 | L10: [Merchandise] Baseball Shirt | M10: 165000 | N10: 15 | O10: =M10*N10 -> 2475000
B11: [Merchandise] T-Shirt | C11: 120000 | D11: 5 | E11: =C11*D11 -> 600000 | G11: [Merchandise] T-Shirt | H11: 120000 | I11: 10 | J11: =H11*I11 -> 1200000 | L11: [Merchandise] T-Shirt | M11: 120000 | N11: 15 | O11: =M11*N11 -> 1800000
B12: [Merchandise] Stickers | C12: 12000 | D12: 20 | E12: =C12*D12 -> 240000 | G12: [Merchandise] Stickers | H12: 12000 | I12: 25 | J12: =H12*I12 -> 300000 | L12: [Merchandise] Stickers | M12: 12000 | N12: 35 | O12: =M12*N12 -> 420000
B13: [Merchandise] Blind Box Keychain | C13: 20000 | D13: 15 | E13: =C13*D13 -> 300000 | G13: [Merchandise] Blind Box Keychain | H13: 20000 | I13: 25 | J13: =H13*I13 -> 500000 | L13: [Merchandise] Blind Box Keychain | M13: 20000 | N13: 35 | O13: =M13*N13 -> 700000
B14: [Merchandise] Keychain AIESEC | C14: 15000 | D14: 5 | E14: =C14*D14 -> 75000 | G14: [Merchandise] Keychain AIESEC | H14: 15000 | I14: 10 | J14: =H14*I14 -> 150000 | L14: [Merchandise] Keychain AIESEC | M14: 15000 | N14: 15 | O14: =M14*N14 -> 225000
B15: [Merchandise] Button Pins | C15: 15000 | D15: 15 | E15: =C15*D15 -> 225000 | G15: [Merchandise] Button Pins | H15: 15000 | I15: 25 | J15: =H15*I15 -> 375000 | L15: [Merchandise] Button Pins | M15: 15000 | N15: 35 | O15: =M15*N15 -> 525000
B16: [Merchandise] Bundle A | C16: 250000 | D16: 10 | E16: =C16*D16 -> 2500000 | G16: [Merchandise] Bundle A | H16: 250000 | I16: 15 | J16: =H16*I16 -> 3750000 | L16: [Merchandise] Bundle A | M16: 250000 | N16: 20 | O16: =M16*N16 -> 5000000
... B23: LCP Pre-Meeting Delegates Fee | C23: 200000 | D23: 27 | E23: =C23*D23 -> 5400000 | G23: LCP Pre-Meeting Delegates Fee | H23: 200000 | I23: 27 | J23: =H23*I23 -> 5400000 | L23: LCP Pre-Meeting Delegates Fee | M23: 200000 | N23: 27 | O23: =M23*N23 -> 5400000
B24: TOTAL REVENUE | E24: =SUM(E5:E9) -> 429325000 | G24: TOTAL REVENUE | J24: =SUM(J5:J9) -> 429650000 | L24: TOTAL REVENUE | O24: =SUM(O5:O9) -> 429975000
B26: Expenses | E26: Total | G26: Expenses | J26: Total | L26: Expenses | O26: Total
B27: =$B$37 -> #REF! | E27: =E74 -> 31044608 | G27: =B27 -> #REF! | J27: =J74 -> 32001933 | L27: =G27 -> #REF! | O27: =O74 -> 34536876
B28: =B76 -> #REF! | E28: =E105 -> 2060700 | G28: =B28 -> #REF! | J28: =J105 -> 1340798 | L28: =G28 -> #REF! | O28: =O105 -> 940036
B29: =B107 -> #REF! | E29: =E127 -> 4652213 | G29: =B29 -> #REF! | J29: =J127 -> 1673697 | L29: =G29 -> #REF! | O29: =O127 -> 2631707
B30: =B129 -> #REF! | E30: =E142 -> 1673000 | G30: =B30 -> #REF! | J30: =J142 -> 536000 | L30: =G30 -> #REF! | O30: =O142 -> 1111000
B31: =B144 -> #REF! | E31: =E155 -> 2120000 | G31: =B31 -> #REF! | J31: =J155 -> 1652320 | L31: =G31 -> #REF! | O31: =O155 -> 1464000
B32: =B157 -> #REF! | E32: =E168 -> 347710200 | G32: =B32 -> #REF! | J32: =J168 -> 361116745 | L32: =G32 -> #REF! | O32: =O168 -> 336554100
B33: TOTAL EXPENSES | E33: =SUM(E27:E32) -> 389260721 | G33: TOTAL EXPENSES | J33: =SUM(J27:J32) -> 398321493 | L33: TOTAL EXPENSES | O33: =SUM(O27:O32) -> 377237719
B34: NET PROFIT | E34: =E24-E33 -> 40064279 | G34: NET PROFIT | J34: =J24-J33 -> 31328507 | L34: NET PROFIT | O34: =O24-O33 -> 52737281
B36: EXPENSE BREAKDOWN | G36: EXPENSE BREAKDOWN | L36: EXPENSE BREAKDOWN
B37: ='🏦COVER🏦'!D11 -> #REF! | C37: P | D37: Q | E37: Total | G37: =B37 -> #REF! | H37: P | I37: Q | J37: Total | L37: =G37 -> #REF! | M37: P | N37: Q | O37: Total
B38: Lanyard CDT | C38: 15000 | D38: 39 | E38: =C38*D38 -> 585000 | F38: =G38 -> Lanyard CDT | G38: Lanyard CDT | H38: 10000 | I38: 39 | J38: =H38*I38 -> 390000 | L38: Lanyard CDT | M38: 9000 | N38: 39 | O38: =M38*N38 -> 351000
B39: Baju CDT | C39: 80000 | D39: 39 | E39: =C39*D39 -> 3120000 | F39: =G39 -> Baju CDT | G39: Baju CDT | H39: 55000 | I39: 40 | J39: =H39*I39 -> 2200000 | L39: Baju CDT | M39: 80000 | N39: 39 | O39: =M39*N39 -> 3120000
B40: Baju Coach + MC WLL | C40: 70000 | D40: 45 | E40: =C40*D40 -> 3150000 | G40: Baju Coach + MC WLL | H40: 55000 | I40: 48 | J40: =H40*I40 -> 2640000 | L40: Baju Coach + MC WLL | M40: 70000 | N40: 45 | O40: =M40*N40 -> 3150000
B41: [Merchandise] Baseball Cap | C41: 45000 | D41: 15 | E41: =C41*D41 -> 675000 | F41: =G41 -> [Merchandise] Baseball Cap | G41: [Merchandise] Baseball Cap | H41: 40000 | I41: 25 | J41: =H41*I41 -> 1000000 | L41: [Merchandise] Baseball Cap | M41: 35000 | N41: 35 | O41: =M41*N41 -> 1225000
B42: [Merchandise] Baseball Shirt | C42: 135000 | D42: 5 | E42: =C42*D42 -> 675000 | F42: =G42 -> [Merchandise] Baseball Shirt | G42: [Merchandise] Baseball Shirt | H42: 120000 | I42: 25 | J42: =H42*I42 -> 3000000 | L42: [Merchandise] Baseball Shirt | M42: 100000 | N42: 35 | O42: =M42*N42 -> 3500000
B43: [Merchandise] T-Shirt | C43: 85000 | D43: 5 | E43: =C43*D43 -> 425000 | G43: [Merchandise] T-Shirt | H43: 80000 | I43: 10 | J43: =H43*I43 -> 800000 | L43: [Merchandise] T-Shirt | M43: 70000 | N43: 15 | O43: =M43*N43 -> 1050000
B44: [Merchandise] Button Pins | C44: 6000 | D44: 110 | E44: =C44*D44 -> 660000 | G44: [Merchandise] Button Pins | H44: 6000 | I44: 135 | J44: =H44*I44 -> 810000 | L44: [Merchandise] Button Pins | M44: 6000 | N44: 160 | O44: =M44*N44 -> 960000
B45: [Merchandise] Blind Box Keychain | C45: 8000 | D45: 110 | E45: =C45*D45 -> 880000 | G45: [Merchandise] Blind Box Keychain | H45: 7000 | I45: 135 | J45: =H45*I45 -> 945000 | L45: [Merchandise] Blind Box Keychain | M45: 6500 | N45: 160 | O45: =M45*N45 -> 1040000
B46: [Merchandise] Keychain | C46: 7000 | D46: 5 | E46: =C46*D46 -> 35000 | G46: [Merchandise] Keychain | H46: 6000 | I46: 10 | J46: =H46*I46 -> 60000 | L46: [Merchandise] Keychain | M46: 5000 | N46: 15 | O46: =M46*N46 -> 75000
B47: [Merchandise] Stickers | C47: 8000 | D47: 59 | E47: =C47*D47 -> 472000 | G47: [Merchandise] Stickers | H47: 5000 | I47: 70 | J47: =H47*I47 -> 350000 | L47: [Merchandise] Stickers | M47: 4000 | N47: 88 | O47: =M47*N47 -> 352000
B48: [CC Corner[ Yupi Hati | C48: 22999 | D48: 2 | E48: =C48*D48 -> 45998 | G48: [CC Corner[ Yupi Hati | H48: 22999 | I48: 3 | J48: =H48*I48 -> 68997 | L48: [CC Corner[ Yupi Hati | M48: 22999 | N48: 4 | O48: =M48*N48 -> 91996
B49: [CC Corner] Yupi | C49: 15000 | D49: 5 | E49: =C49*D49 -> 75000 | G49: [CC Corner] Yupi | H49: 14000 | I49: 8 | J49: =H49*I49 -> 112000 | L49: [CC Corner] Yupi | M49: 12700 | N49: 10 | O49: =M49*N49 -> 127000
B50: [CC Corner] Beng Beng 17g | C50: 44200 | D50: 5 | E50: =C50*D50 -> 221000 | G50: [CC Corner] Beng Beng 17g | H50: 43500 | I50: 5 | J50: =H50*I50 -> 217500 | L50: [CC Corner] Beng Beng 17g | M50: 37600 | N50: 5 | O50: =M50*N50 -> 188000
B51: [CC Corner] Astor Singles 14g | C51: 22000 | D51: 5 | E51: =C51*D51 -> 110000 | G51: [CC Corner] Astor Singles 14g | H51: 20600 | I51: 7 | J51: =H51*I51 -> 144200 | L51: [CC Corner] Astor Singles 14g | M51: 18800 | N51: 10 | O51: =M51*N51 -> 188000
B52: [CC Corner] Permen Relaxa | C52: 8250 | D52: 5 | E52: =C52*D52 -> 41250 | G52: [CC Corner] Permen Relaxa | H52: 8000 | I52: 5 | J52: =H52*I52 -> 40000 | L52: [CC Corner] Permen Relaxa | M52: 6700 | N52: 5 | O52: =M52*N52 -> 33500
B53: [CC Corner] Keripik Chitato 15g | C53: 23400 | D53: 2 | E53: =C53*D53 -> 46800 | G53: [CC Corner] Keripik Chitato 15g | H53: 23000 | I53: 4 | J53: =H53*I53 -> 92000 | L53: [CC Corner] Keripik Chitato 15g | M53: 22000 | N53: 5 | O53: =M53*N53 -> 110000
B54: [CC Corner] Keripik Qtela 20g | C54: 23500 | D54: 2 | E54: =C54*D54 -> 47000 | G54: [CC Corner] Keripik Qtela 20g | H54: 22500 | I54: 4 | J54: =H54*I54 -> 90000 | L54: [CC Corner] Keripik Qtela 20g | M54: 20990 | N54: 5 | O54: =M54*N54 -> 104950
... B66: Emergency Cost | C66: 3000000 | D66: 1 | E66: =C66*D66 -> 3000000 | G66: Emergency Cost | H66: 2000000 | I66: 1 | J66: =H66*I66 -> 2000000 | L66: Emergency Cost | M66: 1500000 | N66: 1 | O66: =M66*N66 -> 1500000
B67: =G67 | E67: 0 | F67: =G67 | J67: =H67*I67 -> 0 | L67: =G67 | O67: 0
B68: =G68 | E68: 0 | F68: =G68 | J68: =H68*I68 -> 0 | L68: =G68 | O68: 0
B69: =G69 | E69: 0 | F69: =G69 | J69: =H69*I69 -> 0 | L69: =G69 | O69: 0
B70: =G70 | E70: 0 | F70: =G70 | J70: =H70*I70 -> 0 | L70: =G70 | O70: 0
B71: =G71 | E71: 0 | F71: =G71 | J71: =H71*I71 -> 0 | L71: =G71 | O71: 0
B72: =G72 | E72: 0 | F72: =G72 | J72: =H72*I72 -> 0 | L72: =G72 | O72: 0
B73: =G73 | E73: 0 | F73: =G73 | J73: =H73*I73 -> 0 | L73: =G73 | O73: 0
B74: TOTAL EXPENSE | E74: =SUM(E38:E73) -> 31044608 | G74: TOTAL EXPENSE | J74: =SUM(J38:J73) -> 32001933 | L74: TOTAL EXPENSE | O74: =SUM(O38:O73) -> 34536876
B76: ='🏦COVER🏦'!D12 -> #REF! | C76: P | D76: Q | E76: Total | G76: =B76 -> #REF! | H76: P | I76: Q | J76: Total | L76: =B76 -> #REF! | M76: P | N76: Q | O76: Total
B77: [CC Party] Amplop putih kecil | C77: 13000 | D77: 2 | E77: =C77*D77 -> 26000 | F77: =G77 -> [CC Party] Amplop putih kecil | G77: [CC Party] Amplop putih kecil | H77: 5150 | I77: 3 | J77: =H77*I77 -> 15450 | L77: [CC Party] Amplop putih kecil | M77: 4500 | N77: 3 | O77: =M77*N77 -> 13500
B78: [CC Party] Print puzzle (kertas karton) | C78: 17000 | D78: 5 | E78: =C78*D78 -> 85000 | F78: =G78 -> [CC Party] Print puzzle (kertas karton) | G78: [CC Party] Print puzzle (kertas karton) | H78: 15000 | I78: 5 | J78: =H78*I78 -> 75000 | L78: [CC Party] Print puzzle (kertas karton) | M78: 10000 | N78: 5 | O78: =M78*N78 -> 50000
B79: [CC Party] print card makanan | C79: 2000 | D79: 20 | E79: =C79*D79 -> 40000 | F79: =G79 -> [CC Party] print card makanan | G79: [CC Party] print card makanan | H79: 1500 | I79: 20 | J79: =H79*I79 -> 30000 | L79: [CC Party] print card makanan | M79: 1000 | N79: 20 | O79: =M79*N79 -> 20000
B80: [CC Party] Jahe | C80: 8000 | D80: 1 | E80: =C80*D80 -> 8000 | F80: =G80 -> [CC Party] Jahe | G80: [CC Party] Jahe | H80: 7000 | I80: 1 | J80: =H80*I80 -> 7000 | L80: [CC Party] Jahe | M80: 5000 | N80: 1 | O80: =M80*N80 -> 5000
B81: [CC Party] Kunyit | C81: 8000 | D81: 1 | E81: =C81*D81 -> 8000 | F81: =G81 -> [CC Party] Kunyit | G81: [CC Party] Kunyit | H81: 7000 | I81: 1 | J81: =H81*I81 -> 7000 | L81: [CC Party] Kunyit | M81: 5000 | N81: 1 | O81: =M81*N81 -> 5000
B82: [CC Party] Lengkuas/Laos | C82: 8000 | D82: 1 | E82: =C82*D82 -> 8000 | F82: =G82 -> [CC Party] Lengkuas/Laos | G82: [CC Party] Lengkuas/Laos | H82: 7000 | I82: 1 | J82: =H82*I82 -> 7000 | L82: [CC Party] Lengkuas/Laos | M82: 5000 | N82: 1 | O82: =M82*N82 -> 5000
B83: [CC Party] Kencur | C83: 10000 | D83: 1 | E83: =C83*D83 -> 10000 | F83: =G83 -> [CC Party] Kencur | G83: [CC Party] Kencur | H83: 8000 | I83: 1 | J83: =H83*I83 -> 8000 | L83: [CC Party] Kencur | M83: 5000 | N83: 1 | O83: =M83*N83 -> 5000
B84: [CC Party] Serai/Sereh | C84: 8000 | D84: 1 | E84: =C84*D84 -> 8000 | F84: =G84 -> [CC Party] Serai/Sereh | G84: [CC Party] Serai/Sereh | H84: 7000 | I84: 1 | J84: =H84*I84 -> 7000 | L84: [CC Party] Serai/Sereh | M84: 5000 | N84: 1 | O84: =M84*N84 -> 5000
B85: [CC Party] Daun Jeruk | C85: 7500 | D85: 1 | E85: =C85*D85 -> 7500 | G85: [CC Party] Daun Jeruk | H85: 5000 | I85: 1 | J85: =H85*I85 -> 5000 | L85: [CC Party] Daun Jeruk | M85: 3000 | N85: 1 | O85: =M85*N85 -> 3000
B86: [CC Party] Kayu manis | C86: 20000 | D86: 1 | E86: =C86*D86 -> 20000 | F86: =G86 -> [CC Party] Kayu manis | G86: [CC Party] Kayu manis | H86: 15000 | I86: 1 | J86: =H86*I86 -> 15000 | L86: [CC Party] Kayu manis | M86: 10000 | N86: 1 | O86: =M86*N86 -> 10000
B87: [CC Party] Ketumbar | C87: 7500 | D87: 1 | E87: =C87*D87 -> 7500 | G87: [CC Party] Ketumbar | H87: 6000 | I87: 1 | J87: =H87*I87 -> 6000 | L87: [CC Party] Ketumbar | M87: 4000 | N87: 1 | O87: =M87*N87 -> 4000
B88: [CC Party] Cengkeh | C88: 9000 | D88: 1 | E88: =C88*D88 -> 9000 | G88: [CC Party] Cengkeh | H88: 7000 | I88: 1 | J88: =H88*I88 -> 7000 | L88: [CC Party] Cengkeh | M88: 4000 | N88: 1 | O88: =M88*N88 -> 4000
B89: [CC Party] Kemiri | C89: 7000 | D89: 1 | E89: =C89*D89 -> 7000 | G89: [CC Party] Kemiri | H89: 5000 | I89: 1 | J89: =H89*I89 -> 5000 | L89: [CC Party] Kemiri | M89: 3000 | N89: 1 | O89: =M89*N89 -> 3000
B90: [CC Party] Sertificate RnR | C90: 5000 | D90: 4 | E90: =C90*D90 -> 20000 | G90: [CC Party] Sertificate RnR | H90: 4000 | I90: 4 | J90: =H90*I90 -> 16000 | L90: [CC Party] Sertificate RnR | M90: 3000 | N90: 4 | O90: =M90*N90 -> 12000
B91: [CC Party] Gift RnR | C91: 65000 | D91: 4 | E91: =C91*D91 -> 260000 | G91: [CC Party] Gift RnR | H91: 50000 | I91: 4 | J91: =H91*I91 -> 200000 | L91: [CC Party] Gift RnR | M91: 40000 | N91: 4 | O91: =M91*N91 -> 160000
B92: [FACI Needs] | C92: 700000 | D92: 1 | E92: =C92*D92 -> 700000 | G92: [FACI Needs] | H92: 500000 | I92: 1 | J92: =H92*I92 -> 500000 | L92: [FACI Needs] | M92: 400000 | N92: 1 | O92: =M92*N92 -> 400000
B93: Print Cover Cue Card + Laminating | C93: 5000 | D93: 2 | E93: =C93*D93 -> 10000 | G93: Print Cover Cue Card + Laminating | H93: 4000 | I93: 2 | J93: =H93*I93 -> 8000 | L93: Print Cover Cue Card + Laminating | M93: 3000 | N93: 2 | O93: =M93*N93 -> 6000
B94: [WLL] Karton A1 | C94: 10000 | D94: 4 | E94: =C94*D94 -> 40000 | G94: [WLL] Karton A1 | H94: 8000 | I94: 3 | J94: =H94*I94 -> 24000 | L94: [WLL] Karton A1 | M94: 6500 | N94: 2 | O94: =M94*N94 -> 13000
B95: [WLL] Cat Warna Pink 100ml | C95: 11000 | D95: 4 | E95: =C95*D95 -> 44000 | G95: [WLL] Cat Warna Pink 100ml | H95: 11000 | I95: 3 | J95: =H95*I95 -> 33000 | L95: [WLL] Cat Warna Pink 100ml | M95: 11000 | N95: 2 | O95: =M95*N95 -> 22000
B96: [WLL] Cat Warna Kuning 100ml | C96: 11000 | D96: 4 | E96: =C96*D96 -> 44000 | G96: [WLL] Cat Warna Kuning 100ml | H96: 11000 | I96: 3 | J96: =H96*I96 -> 33000 | L96: [WLL] Cat Warna Kuning 100ml | M96: 11000 | N96: 2 | O96: =M96*N96 -> 22000
B97: [WLL] Cat Warna Hijau 100ml | C97: 11000 | D97: 4 | E97: =C97*D97 -> 44000 | G97: [WLL] Cat Warna Hijau 100ml | H97: 11000 | I97: 3 | J97: =H97*I97 -> 33000 | L97: [WLL] Cat Warna Hijau 100ml | M97: 11000 | N97: 2 | O97: =M97*N97 -> 22000
B98: [WLL] Cat Warna Biru Muda 100ml | C98: 11000 | D98: 4 | E98: =C98*D98 -> 44000 | G98: [WLL] Cat Warna Biru Muda 100ml | H98: 11000 | I98: 3 | J98: =H98*I98 -> 33000 | L98: [WLL] Cat Warna Biru Muda 100ml | M98: 11000 | N98: 2 | O98: =M98*N98 -> 22000
... B103: [Global Village] Print Stamp Card Custom | C103: 500 | D103: 323 | E103: =C103*D103 -> 161500 | G103: [Global Village] Print Stamp Card Custom | H103: 300 | I103: 325 | J103: =H103*I103 -> 97500 | L103: [Global Village] Print Stamp Card Custom | M103: 150 | N103: 330 | O103: =M103*N103 -> 49500
B104: Printing Placard NLF & NLM | C104: 50000 | D104: 1 | E104: =C104*D104 -> 50000 | F104: =G104 -> Printing Placard NLF & NLM | G104: Printing Placard NLF & NLM | H104: 40000 | I104: 1 | J104: =H104*I104 -> 40000 | L104: Printing Placard NLF & NLM | M104: 35000 | N104: 1 | O104: =M104*N104 -> 35000
B105: TOTAL EXPENSE | E105: =SUM(E77:E104) -> 2060700 | F105: [Program] Logistics | G105: TOTAL EXPENSE | J105: =SUM(J80:J104) -> 1340798 | L105: TOTAL EXPENSE | O105: =SUM(O80:O104) -> 940036
B107: ='🏦COVER🏦'!D13 -> #REF! | C107: P | D107: Q | E107: Total | G107: =B107 -> #REF! | H107: P | I107: Q | J107: Total | L107: =B107 -> #REF! | M107: P | N107: Q | O107: Total
B108: Delegates ID Card | C108: 1349 | D108: 323 | E108: =C108*D108 -> 435727 | F108: =G108 -> Delegates ID Card | G108: Delegates ID Card | H108: 955 | J108: =H108*I108 -> 0 | L108: Delegates ID Card | M108: 952 | N108: 330 | O108: =M108*N108 -> 314160
B109: Sugarcubes Envelope (100 pcs) | C109: 27660 | D109: 4 | E109: =C109*D109 -> 110640 | F109: =G109 -> Sugarcubes Envelope (100 pcs) | G109: Sugarcubes Envelope (100 pcs) | H109: 22500 | I109: 4 | J109: =H109*I109 -> 90000 | L109: Sugarcubes Envelope (100 pcs) | M109: 22000 | N109: 4 | O109: =M109*N109 -> 88000
B110: Delegates Kit | C110: 10000 | D110: 323 | E110: =C110*D110 -> 3230000 | F110: =G110 -> Delegates Kit | G110: Delegates Kit | H110: 3000 | I110: 300 | J110: =H110*I110 -> 900000 | L110: Delegates Kit | M110: 5000 | N110: 330 | O110: =M110*N110 -> 1650000
B111: [Medicine] Mylanta | C111: 11681 | D111: 1 | E111: =C111*D111 -> 11681 | F111: =G111 -> [Medicine] Mylanta | G111: [Medicine] Mylanta | H111: 10700 | I111: 1 | J111: =H111*I111 -> 10700 | L111: [Medicine] Mylanta | M111: 10000 | N111: 1 | O111: =M111*N111 -> 10000
B112: [Medicine] Sanmol | C112: 4500 | D112: 4 | E112: =C112*D112 -> 18000 | F112: =G112 -> [Medicine] Sanmol | G112: [Medicine] Sanmol | H112: 2500 | I112: 4 | J112: =H112*I112 -> 10000 | L112: [Medicine] Sanmol | M112: 2000 | N112: 4 | O112: =M112*N112 -> 8000
B113: [Medicine] Tolak Angin | C113: 63700 | D113: 1 | E113: =C113*D113 -> 63700 | F113: =G113 -> [Medicine] Tolak Angin | G113: [Medicine] Tolak Angin | H113: 57950 | I113: 1 | J113: =H113*I113 -> 57950 | L113: [Medicine] Tolak Angin | M113: 55000 | N113: 1 | O113: =M113*N113 -> 55000
B114: [Medicine] Minyak Kayu Putih (S) | C114: 16600 | D114: 1 | E114: =C114*D114 -> 16600 | F114: =G114 -> [Medicine] Minyak Kayu Putih (S) | G114: [Medicine] Minyak Kayu Putih (S) | H114: 14000 | I114: 1 | J114: =H114*I114 -> 14000 | L114: [Medicine] Minyak Kayu Putih (S) | M114: 13794 | N114: 1 | O114: =M114*N114 -> 13794
B115: [Medicine] Decolgen FX | C115: 15300 | D115: 1 | E115: =C115*D115 -> 15300 | F115: =G115 -> [Medicine] Decolgen FX | G115: [Medicine] Decolgen FX | H115: 15200 | I115: 1 | J115: =H115*I115 -> 15200 | L115: [Medicine] Decolgen FX | M115: 13800 | N115: 1 | O115: =M115*N115 -> 13800
B116: [Medicine] Hansaplast | C116: 15500 | D116: 2 | E116: =C116*D116 -> 31000 | F116: =G116 -> [Medicine] Hansaplast | G116: [Medicine] Hansaplast | H116: 11572 | I116: 2 | J116: =H116*I116 -> 23144 | L116: [Medicine] Hansaplast | M116: 10900 | N116: 2 | O116: =M116*N116 -> 21800
B117: [Medicine] Betadine (S) | C117: 24150 | D117: 1 | E117: =C117*D117 -> 24150 | G117: [Medicine] Betadine (S) | H117: 20778 | I117: 1 | J117: =H117*I117 -> 20778 | L117: [Medicine] Betadine (S) | M117: 18663 | N117: 1 | O117: =M117*N117 -> 18663
B118: [Medicine] Kain Kassa | C118: 10000 | D118: 1 | E118: =C118*D118 -> 10000 | G118: [Medicine] Kain Kassa | H118: 9257 | I118: 1 | J118: =H118*I118 -> 9257 | L118: [Medicine] Kain Kassa | M118: 8500 | N118: 1 | O118: =M118*N118 -> 8500
B119: [Medicine] Hansaplast Plester Roll | C119: 15895 | D119: 1 | E119: =C119*D119 -> 15895 | G119: [Medicine] Hansaplast Plester Roll | H119: 15043 | I119: 1 | J119: =H119*I119 -> 15043 | L119: [Medicine] Hansaplast Plester Roll | M119: 14690 | N119: 1 | O119: =M119*N119 -> 14690
B120: [Medicine] Pads / Pembalut | C120: 31510 | D120: 2 | E120: =C120*D120 -> 63020 | G120: [Medicine] Pads / Pembalut | H120: 29000 | I120: 2 | J120: =H120*I120 -> 58000 | L120: [Medicine] Pads / Pembalut | M120: 28400 | N120: 2 | O120: =M120*N120 -> 56800
B121: Double Tape | C121: 8500 | D121: 5 | E121: =C121*D121 -> 42500 | G121: Double Tape | H121: 6125 | I121: 5 | J121: =H121*I121 -> 30625 | L121: Double Tape | M121: 6000 | N121: 5 | O121: =M121*N121 -> 30000
B122: Print Foto + Nama Delegates | C122: 3000 | D122: 40 | E122: =C122*D122 -> 120000 | G122: Print Foto + Nama Delegates | H122: 2000 | I122: 45 | J122: =H122*I122 -> 90000 | L122: Print Foto + Nama Delegates | M122: 1500 | N122: 50 | O122: =M122*N122 -> 75000
B123: Print Nametag Delegates | C123: 3000 | D123: 80 | E123: =C123*D123 -> 240000 | G123: Print Nametag Delegates | H123: 2000 | I123: 82 | J123: =H123*I123 -> 164000 | L123: Print Nametag Delegates | M123: 1500 | N123: 85 | O123: =M123*N123 -> 127500
B124: Stickers RnR | C124: 6000 | D124: 3 | E124: =C124*D124 -> 18000 | G124: Stickers RnR | H124: 5000 | I124: 3 | J124: =H124*I124 -> 15000 | L124: Stickers RnR | M124: 4000 | N124: 3 | O124: =M124*N124 -> 12000
B125: RnR Certificate | C125: 12000 | D125: 3 | E125: =C125*D125 -> 36000 | G125: RnR Certificate | H125: 10000 | I125: 3 | J125: =H125*I125 -> 30000 | L125: RnR Certificate | M125: 8000 | N125: 3 | O125: =M125*N125 -> 24000
...

Sheet Copy of 💰BUDGET PLAN💰
B1: =CONCATENATE('🏦COVER🏦'!D7," 💰Budget Plan💰") -> #REF!
B2: 💔Pessimistic Plan💔 | G2: 🤍Realistic Plan🤍 | L2: 💗Optimistic Plan💗
B3: REVENUE BREAKDOWN | G3: REVENUE BREAKDOWN | L3: REVENUE BREAKDOWN
B4: (revenue stream) | C4: P | D4: Q | E4: Total | G4: (revenue stream) | H4: P | I4: Q | J4: Total | L4: (revenue stream) | M4: P | N4: Q | O4: Total
B5: Delegates Fee | C5: 1150000 | D5: 320 | E5: =C5*D5 -> 368000000 | G5: Delegates Fee | H5: 1150000 | I5: 320 | J5: =H5*I5 -> 368000000 | L5: Delegates Fee | M5: 1150000 | N5: 320 | O5: =M5*N5 -> 368000000
B6: International Delegates Fee | C6: 1500000 | D6: 3 | E6: =C6*D6 -> 4500000 | G6: International Delegates Fee | H6: 1500000 | I6: 5 | J6: =H6*I6 -> 7500000 | L6: International Delegates Fee | M6: 1500000 | N6: 10 | O6: =M6*N6 -> 15000000
B7: Commitment Fee | C7: 50000 | D7: 323 | E7: =C7*D7 -> 16150000 | G7: Commitment Fee | H7: 50000 | I7: 325 | J7: =H7*I7 -> 16250000 | L7: Commitment Fee | M7: 50000 | N7: 330 | O7: =M7*N7 -> 16500000
B8: Working Capital from MC | C8: 40000000 | D8: 1 | E8: =C8*D8 -> 40000000 | G8: Working Capital from MC | H8: 40000000 | I8: 1 | J8: =H8*I8 -> 40000000 | L8: Working Capital from MC | M8: 40000000 | N8: 1 | O8: =M8*N8 -> 40000000
B9: Working Capital from LC | C9: 5000000 | D9: 1 | E9: =C9*D9 -> 5000000 | G9: Working Capital from LC | H9: 5000000 | I9: 1 | J9: =H9*I9 -> 5000000 | L9: Working Capital from LC | M9: 5000000 | N9: 1 | O9: =M9*N9 -> 5000000
B10: [Merchandise] Baseball Cap | C10: 65000 | D10: 5 | E10: =C10*D10 -> 325000 | G10: [Merchandise] Baseball Cap | H10: 65000 | I10: 10 | J10: =H10*I10 -> 650000 | L10: [Merchandise] Baseball Cap | M10: 65000 | N10: 15 | O10: =M10*N10 -> 975000
B11: [Merchandise] Baseball Shirt | C11: 165000 | D11: 5 | E11: =C11*D11 -> 825000 | G11: [Merchandise] Baseball Shirt | H11: 165000 | I11: 10 | J11: =H11*I11 -> 1650000 | L11: [Merchandise] Baseball Shirt | M11: 165000 | N11: 15 | O11: =M11*N11 -> 2475000
B12: [Merchandise] T-Shirt | C12: 120000 | D12: 5 | E12: =C12*D12 -> 600000 | G12: [Merchandise] T-Shirt | H12: 120000 | I12: 10 | J12: =H12*I12 -> 1200000 | L12: [Merchandise] T-Shirt | M12: 120000 | N12: 15 | O12: =M12*N12 -> 1800000
B13: [Merchandise] Stickers | C13: 12000 | D13: 20 | E13: =C13*D13 -> 240000 | G13: [Merchandise] Stickers | H13: 12000 | I13: 25 | J13: =H13*I13 -> 300000 | L13: [Merchandise] Stickers | M13: 12000 | N13: 35 | O13: =M13*N13 -> 420000
B14: [Merchandise] Blind Box Keychain | C14: 20000 | D14: 15 | E14: =C14*D14 -> 300000 | G14: [Merchandise] Blind Box Keychain | H14: 20000 | I14: 25 | J14: =H14*I14 -> 500000 | L14: [Merchandise] Blind Box Keychain | M14: 20000 | N14: 35 | O14: =M14*N14 -> 700000
B15: [Merchandise] Keychain AIESEC | C15: 15000 | D15: 5 | E15: =C15*D15 -> 75000 | G15: [Merchandise] Keychain AIESEC | H15: 15000 | I15: 10 | J15: =H15*I15 -> 150000 | L15: [Merchandise] Keychain AIESEC | M15: 15000 | N15: 15 | O15: =M15*N15 -> 225000
B16: [Merchandise] Button Pins | C16: 15000 | D16: 15 | E16: =C16*D16 -> 225000 | G16: [Merchandise] Button Pins | H16: 15000 | I16: 25 | J16: =H16*I16 -> 375000 | L16: [Merchandise] Button Pins | M16: 15000 | N16: 35 | O16: =M16*N16 -> 525000
... B26: Baju CDT | C26: 80000 | D26: 39 | E26: =C26*D26 -> 3120000 | G26: Baju CDT | H26: 80000 | I26: 39 | J26: =H26*I26 -> 3120000 | L26: Baju CDT | M26: 80000 | N26: 39 | O26: =M26*N26 -> 3120000
B27: TOTAL REVENUE | E27: =SUM(E5:E10) -> 433975000 | G27: TOTAL REVENUE | J27: =SUM(J5:J10) -> 437400000 | L27: TOTAL REVENUE | O27: =SUM(O5:O10) -> 445475000
B29: Expenses | E29: Total | G29: Expenses | J29: Total | L29: Expenses | O29: Total
B30: =$B$40 -> #REF! | E30: =E79 -> 31112608 | G30: =B30 -> #REF! | J30: =J79 -> 33496933 | L30: =G30 -> #REF! | O30: =O79 -> 34598876
B31: =B81 -> #REF! | E31: =E110 -> 2060700 | G31: =B31 -> #REF! | J31: =J110 -> 1340798 | L31: =G31 -> #REF! | O31: =O110 -> 940036
B32: =B112 -> #REF! | E32: =E132 -> 4652213 | G32: =B32 -> #REF! | J32: =J132 -> 3684072 | L32: =G32 -> #REF! | O32: =O132 -> 2631707
B33: =B134 -> #REF! | E33: =E147 -> 1673000 | G33: =B33 -> #REF! | J33: =J147 -> 1408000 | L33: =G33 -> #REF! | O33: =O147 -> 1111000
B34: =B149 -> #REF! | E34: =E160 -> 2120000 | G34: =B34 -> #REF! | J34: =J160 -> 1652320 | L34: =G34 -> #REF! | O34: =O160 -> 1464000
B35: =B162 -> #REF! | E35: =E174 -> 375905200 | G35: =B35 -> #REF! | J35: =J174 -> 380686745 | L35: =G35 -> #REF! | O35: =O174 -> 363914100
B36: TOTAL EXPENSES | E36: =SUM(E30:E35) -> 417523721 | G36: TOTAL EXPENSES | J36: =SUM(J30:J35) -> 422268868 | L36: TOTAL EXPENSES | O36: =SUM(O30:O35) -> 404659719
B37: NET PROFIT | E37: =E27-E36 -> 16451279 | G37: NET PROFIT | J37: =J27-J36 -> 15131132 | L37: NET PROFIT | O37: =O27-O36 -> 40815281
B39: EXPENSE BREAKDOWN | G39: EXPENSE BREAKDOWN | L39: EXPENSE BREAKDOWN
B40: ='🏦COVER🏦'!D11 -> #REF! | C40: P | D40: Q | E40: Total | G40: =B40 -> #REF! | H40: P | I40: Q | J40: Total | L40: =G40 -> #REF! | M40: P | N40: Q | O40: Total
B41: Lanyard CDT | C41: 15000 | D41: 39 | E41: =C41*D41 -> 585000 | F41: =G41 -> Lanyard CDT | G41: Lanyard CDT | H41: 10000 | I41: 39 | J41: =H41*I41 -> 390000 | L41: Lanyard CDT | M41: 9000 | N41: 39 | O41: =M41*N41 -> 351000
B42: Baju CDT | C42: 80000 | D42: 39 | E42: =C42*D42 -> 3120000 | F42: =G42 -> Baju CDT | G42: Baju CDT | H42: 80000 | I42: 39 | J42: =H42*I42 -> 3120000 | L42: Baju CDT | M42: 80000 | N42: 39 | O42: =M42*N42 -> 3120000
B43: Baju Coach + MC WLL | C43: 70000 | D43: 45 | E43: =C43*D43 -> 3150000 | G43: Baju Coach + MC WLL | H43: 70000 | I43: 45 | J43: =H43*I43 -> 3150000 | L43: Baju Coach + MC WLL | M43: 70000 | N43: 45 | O43: =M43*N43 -> 3150000
B44: [Merchandise] Baseball Cap | C44: 45000 | D44: 15 | E44: =C44*D44 -> 675000 | F44: =G44 -> [Merchandise] Baseball Cap | G44: [Merchandise] Baseball Cap | H44: 40000 | I44: 25 | J44: =H44*I44 -> 1000000 | L44: [Merchandise] Baseball Cap | M44: 35000 | N44: 35 | O44: =M44*N44 -> 1225000
B45: [Merchandise] Baseball Shirt | C45: 135000 | D45: 5 | E45: =C45*D45 -> 675000 | F45: =G45 -> [Merchandise] Baseball Shirt | G45: [Merchandise] Baseball Shirt | H45: 120000 | I45: 25 | J45: =H45*I45 -> 3000000 | L45: [Merchandise] Baseball Shirt | M45: 100000 | N45: 35 | O45: =M45*N45 -> 3500000
B46: [Merchandise] T-Shirt | C46: 85000 | D46: 5 | E46: =C46*D46 -> 425000 | G46: [Merchandise] T-Shirt | H46: 80000 | I46: 10 | J46: =H46*I46 -> 800000 | L46: [Merchandise] T-Shirt | M46: 70000 | N46: 15 | O46: =M46*N46 -> 1050000
B47: [Merchandise] Button Pins | C47: 6000 | D47: 110 | E47: =C47*D47 -> 660000 | G47: [Merchandise] Button Pins | H47: 6000 | I47: 135 | J47: =H47*I47 -> 810000 | L47: [Merchandise] Button Pins | M47: 6000 | N47: 160 | O47: =M47*N47 -> 960000
B48: [Merchandise] Blind Box Keychain | C48: 8000 | D48: 110 | E48: =C48*D48 -> 880000 | G48: [Merchandise] Blind Box Keychain | H48: 7000 | I48: 135 | J48: =H48*I48 -> 945000 | L48: [Merchandise] Blind Box Keychain | M48: 6500 | N48: 160 | O48: =M48*N48 -> 1040000
B49: [Merchandise] Keychain | C49: 7000 | D49: 5 | E49: =C49*D49 -> 35000 | G49: [Merchandise] Keychain | H49: 6000 | I49: 10 | J49: =H49*I49 -> 60000 | L49: [Merchandise] Keychain | M49: 5000 | N49: 15 | O49: =M49*N49 -> 75000
B50: [Merchandise] Stickers | C50: 8000 | D50: 59 | E50: =C50*D50 -> 472000 | G50: [Merchandise] Stickers | H50: 5000 | I50: 70 | J50: =H50*I50 -> 350000 | L50: [Merchandise] Stickers | M50: 4000 | N50: 88 | O50: =M50*N50 -> 352000
B51: [CC Corner] Print Paper for Drawing Photobooth | C51: 10000 | D51: 5 | E51: =C51*D51 -> 50000 | G51: [CC Corner] Print Paper for Drawing Photobooth | H51: 7000 | I51: 7 | J51: =H51*I51 -> 49000 | L51: [CC Corner] Print Paper for Drawing Photobooth | M51: 5000 | N51: 10 | O51: =M51*N51 -> 50000
B52: [CC Corner] Drawing Marker | C52: 10000 | D52: 2 | E52: =C52*D52 -> 20000 | G52: [CC Corner] Drawing Marker | H52: 9000 | I52: 2 | J52: =H52*I52 -> 18000 | L52: [CC Corner] Drawing Marker | M52: 7000 | N52: 2 | O52: =M52*N52 -> 14000
B53: [CC Corner[ Yupi Hati | C53: 22999 | D53: 2 | E53: =C53*D53 -> 45998 | G53: [CC Corner[ Yupi Hati | H53: 22999 | I53: 3 | J53: =H53*I53 -> 68997 | L53: [CC Corner[ Yupi Hati | M53: 22999 | N53: 4 | O53: =M53*N53 -> 91996
B54: [CC Corner] Yupi | C54: 15000 | D54: 5 | E54: =C54*D54 -> 75000 | G54: [CC Corner] Yupi | H54: 14000 | I54: 8 | J54: =H54*I54 -> 112000 | L54: [CC Corner] Yupi | M54: 12700 | N54: 10 | O54: =M54*N54 -> 127000
B55: [CC Corner] Beng Beng 17g | C55: 44200 | D55: 5 | E55: =C55*D55 -> 221000 | G55: [CC Corner] Beng Beng 17g | H55: 43500 | I55: 5 | J55: =H55*I55 -> 217500 | L55: [CC Corner] Beng Beng 17g | M55: 37600 | N55: 5 | O55: =M55*N55 -> 188000
B56: [CC Corner] Astor Singles 14g | C56: 22000 | D56: 5 | E56: =C56*D56 -> 110000 | G56: [CC Corner] Astor Singles 14g | H56: 20600 | I56: 7 | J56: =H56*I56 -> 144200 | L56: [CC Corner] Astor Singles 14g | M56: 18800 | N56: 10 | O56: =M56*N56 -> 188000
B57: [CC Corner] Permen Relaxa | C57: 8250 | D57: 5 | E57: =C57*D57 -> 41250 | G57: [CC Corner] Permen Relaxa | H57: 8000 | I57: 5 | J57: =H57*I57 -> 40000 | L57: [CC Corner] Permen Relaxa | M57: 6700 | N57: 5 | O57: =M57*N57 -> 33500
... B71: Emergency Cost | C71: 3000000 | D71: 1 | E71: =C71*D71 -> 3000000 | G71: Emergency Cost | H71: 2000000 | I71: 1 | J71: =H71*I71 -> 2000000 | L71: Emergency Cost | M71: 1500000 | N71: 1 | O71: =M71*N71 -> 1500000
B72: =G72 | E72: 0 | F72: =G72 | J72: =H72*I72 -> 0 | L72: =G72 | O72: 0
B73: =G73 | E73: 0 | F73: =G73 | J73: =H73*I73 -> 0 | L73: =G73 | O73: 0
B74: =G74 | E74: 0 | F74: =G74 | J74: =H74*I74 -> 0 | L74: =G74 | O74: 0
B75: =G75 | E75: 0 | F75: =G75 | J75: =H75*I75 -> 0 | L75: =G75 | O75: 0
B76: =G76 | E76: 0 | F76: =G76 | J76: =H76*I76 -> 0 | L76: =G76 | O76: 0
B77: =G77 | E77: 0 | F77: =G77 | J77: =H77*I77 -> 0 | L77: =G77 | O77: 0
B78: =G78 | E78: 0 | F78: =G78 | J78: =H78*I78 -> 0 | L78: =G78 | O78: 0
B79: TOTAL EXPENSE | E79: =SUM(E41:E78) -> 31112608 | G79: TOTAL EXPENSE | J79: =SUM(J41:J78) -> 33496933 | L79: TOTAL EXPENSE | O79: =SUM(O41:O78) -> 34598876
B81: ='🏦COVER🏦'!D12 -> #REF! | C81: P | D81: Q | E81: Total | G81: =B81 -> #REF! | H81: P | I81: Q | J81: Total | L81: =B81 -> #REF! | M81: P | N81: Q | O81: Total
B82: [CC Party] Amplop putih kecil | C82: 13000 | D82: 2 | E82: =C82*D82 -> 26000 | F82: =G82 -> [CC Party] Amplop putih kecil | G82: [CC Party] Amplop putih kecil | H82: 5150 | I82: 3 | J82: =H82*I82 -> 15450 | L82: [CC Party] Amplop putih kecil | M82: 4500 | N82: 3 | O82: =M82*N82 -> 13500
B83: [CC Party] Print puzzle (kertas karton) | C83: 17000 | D83: 5 | E83: =C83*D83 -> 85000 | F83: =G83 -> [CC Party] Print puzzle (kertas karton) | G83: [CC Party] Print puzzle (kertas karton) | H83: 15000 | I83: 5 | J83: =H83*I83 -> 75000 | L83: [CC Party] Print puzzle (kertas karton) | M83: 10000 | N83: 5 | O83: =M83*N83 -> 50000
B84: [CC Party] print card makanan | C84: 2000 | D84: 20 | E84: =C84*D84 -> 40000 | F84: =G84 -> [CC Party] print card makanan | G84: [CC Party] print card makanan | H84: 1500 | I84: 20 | J84: =H84*I84 -> 30000 | L84: [CC Party] print card makanan | M84: 1000 | N84: 20 | O84: =M84*N84 -> 20000
B85: [CC Party] Jahe | C85: 8000 | D85: 1 | E85: =C85*D85 -> 8000 | F85: =G85 -> [CC Party] Jahe | G85: [CC Party] Jahe | H85: 7000 | I85: 1 | J85: =H85*I85 -> 7000 | L85: [CC Party] Jahe | M85: 5000 | N85: 1 | O85: =M85*N85 -> 5000
B86: [CC Party] Kunyit | C86: 8000 | D86: 1 | E86: =C86*D86 -> 8000 | F86: =G86 -> [CC Party] Kunyit | G86: [CC Party] Kunyit | H86: 7000 | I86: 1 | J86: =H86*I86 -> 7000 | L86: [CC Party] Kunyit | M86: 5000 | N86: 1 | O86: =M86*N86 -> 5000
B87: [CC Party] Lengkuas/Laos | C87: 8000 | D87: 1 | E87: =C87*D87 -> 8000 | F87: =G87 -> [CC Party] Lengkuas/Laos | G87: [CC Party] Lengkuas/Laos | H87: 7000 | I87: 1 | J87: =H87*I87 -> 7000 | L87: [CC Party] Lengkuas/Laos | M87: 5000 | N87: 1 | O87: =M87*N87 -> 5000
B88: [CC Party] Kencur | C88: 10000 | D88: 1 | E88: =C88*D88 -> 10000 | F88: =G88 -> CC Party] Kencur | G88: CC Party] Kencur | H88: 8000 | I88: 1 | J88: =H88*I88 -> 8000 | L88: CC Party] Kencur | M88: 5000 | N88: 1 | O88: =M88*N88 -> 5000
B89: [CC Party] Serai/Sereh | C89: 8000 | D89: 1 | E89: =C89*D89 -> 8000 | F89: =G89 -> [CC Party] Serai/Sereh | G89: [CC Party] Serai/Sereh | H89: 7000 | I89: 1 | J89: =H89*I89 -> 7000 | L89: [CC Party] Serai/Sereh | M89: 5000 | N89: 1 | O89: =M89*N89 -> 5000
B90: [CC Party] Daun Jeruk | C90: 7500 | D90: 1 | E90: =C90*D90 -> 7500 | G90: CC Party] Daun Jeruk | H90: 5000 | I90: 1 | J90: =H90*I90 -> 5000 | L90: CC Party] Daun Jeruk | M90: 3000 | N90: 1 | O90: =M90*N90 -> 3000
B91: [CC Party] Kayu manis | C91: 20000 | D91: 1 | E91: =C91*D91 -> 20000 | F91: =G91 -> CC Party] Kayu manis | G91: CC Party] Kayu manis | H91: 15000 | I91: 1 | J91: =H91*I91 -> 15000 | L91: CC Party] Kayu manis | M91: 10000 | N91: 1 | O91: =M91*N91 -> 10000
B92: [CC Party] Ketumbar | C92: 7500 | D92: 1 | E92: =C92*D92 -> 7500 | G92: CC Party] Ketumbar | H92: 6000 | I92: 1 | J92: =H92*I92 -> 6000 | L92: CC Party] Ketumbar | M92: 4000 | N92: 1 | O92: =M92*N92 -> 4000
B93: [CC Party] Cengkeh | C93: 9000 | D93: 1 | E93: =C93*D93 -> 9000 | G93: CC Party] Cengkeh | H93: 7000 | I93: 1 | J93: =H93*I93 -> 7000 | L93: CC Party] Cengkeh | M93: 4000 | N93: 1 | O93: =M93*N93 -> 4000
B94: [CC Party] Kemiri | C94: 7000 | D94: 1 | E94: =C94*D94 -> 7000 | G94: CC Party] Kemiri | H94: 5000 | I94: 1 | J94: =H94*I94 -> 5000 | L94: CC Party] Kemiri | M94: 3000 | N94: 1 | O94: =M94*N94 -> 3000
B95: [CC Party] Sertificate RnR | C95: 5000 | D95: 4 | E95: =C95*D95 -> 20000 | G95: CC Party] Sertificate RnR | H95: 4000 | I95: 4 | J95: =H95*I95 -> 16000 | L95: CC Party] Sertificate RnR | M95: 3000 | N95: 4 | O95: =M95*N95 -> 12000
B96: [CC Party] Gift RnR | C96: 65000 | D96: 4 | E96: =C96*D96 -> 260000 | G96: [CC Party] Gift RnR | H96: 50000 | I96: 4 | J96: =H96*I96 -> 200000 | L96: [CC Party] Gift RnR | M96: 40000 | N96: 4 | O96: =M96*N96 -> 160000
B97: [FACI Needs] | C97: 700000 | D97: 1 | E97: =C97*D97 -> 700000 | G97: [FACI Needs] | H97: 500000 | I97: 1 | J97: =H97*I97 -> 500000 | L97: [FACI Needs] | M97: 400000 | N97: 1 | O97: =M97*N97 -> 400000
B98: Print Cover Cue Card + Laminating | C98: 5000 | D98: 2 | E98: =C98*D98 -> 10000 | G98: Print Cover Cue Card + Laminating | H98: 4000 | I98: 2 | J98: =H98*I98 -> 8000 | L98: Print Cover Cue Card + Laminating | M98: 3000 | N98: 2 | O98: =M98*N98 -> 6000
B99: [WLL] Karton A1 | C99: 10000 | D99: 4 | E99: =C99*D99 -> 40000 | G99: [WLL] Karton A1 | H99: 8000 | I99: 3 | J99: =H99*I99 -> 24000 | L99: [WLL] Karton A1 | M99: 6500 | N99: 2 | O99: =M99*N99 -> 13000
B100: [WLL] Cat Warna Pink 100ml | C100: 11000 | D100: 4 | E100: =C100*D100 -> 44000 | G100: [WLL] Cat Warna Pink 100ml | H100: 11000 | I100: 3 | J100: =H100*I100 -> 33000 | L100: [WLL] Cat Warna Pink 100ml | M100: 11000 | N100: 2 | O100: =M100*N100 -> 22000
B101: [WLL] Cat Warna Kuning 100ml | C101: 11000 | D101: 4 | E101: =C101*D101 -> 44000 | G101: [WLL] Cat Warna Kuning 100ml | H101: 11000 | I101: 3 | J101: =H101*I101 -> 33000 | L101: [WLL] Cat Warna Kuning 100ml | M101: 11000 | N101: 2 | O101: =M101*N101 -> 22000
B102: [WLL] Cat Warna Hijau 100ml | C102: 11000 | D102: 4 | E102: =C102*D102 -> 44000 | G102: [WLL] Cat Warna Hijau 100ml | H102: 11000 | I102: 3 | J102: =H102*I102 -> 33000 | L102: [WLL] Cat Warna Hijau 100ml | M102: 11000 | N102: 2 | O102: =M102*N102 -> 22000
B103: [WLL] Cat Warna Biru Muda 100ml | C103: 11000 | D103: 4 | E103: =C103*D103 -> 44000 | G103: [WLL] Cat Warna Biru Muda 100ml | H103: 11000 | I103: 3 | J103: =H103*I103 -> 33000 | L103: [WLL] Cat Warna Biru Muda 100ml | M103: 11000 | N103: 2 | O103: =M103*N103 -> 22000
... B108: [Global Village] Print Stamp Card Custom | C108: 500 | D108: 323 | E108: =C108*D108 -> 161500 | G108: [Global Village] Print Stamp Card Custom | H108: 300 | I108: 325 | J108: =H108*I108 -> 97500 | L108: [Global Village] Print Stamp Card Custom | M108: 150 | N108: 330 | O108: =M108*N108 -> 49500
B109: Printing Placard NLF & NLM | C109: 50000 | D109: 1 | E109: =C109*D109 -> 50000 | F109: =G109 -> Printing Placard NLF & NLM | G109: Printing Placard NLF & NLM | H109: 40000 | I109: 1 | J109: =H109*I109 -> 40000 | L109: Printing Placard NLF & NLM | M109: 35000 | N109: 1 | O109: =M109*N109 -> 35000
B110: TOTAL EXPENSE | E110: =SUM(E82:E109) -> 2060700 | F110: [Program] Logistics | G110: TOTAL EXPENSE | J110: =SUM(J85:J109) -> 1340798 | L110: TOTAL EXPENSE | O110: =SUM(O85:O109) -> 940036
B112: ='🏦COVER🏦'!D13 -> #REF! | C112: P | D112: Q | E112: Total | G112: =B112 -> #REF! | H112: P | I112: Q | J112: Total | L112: =B112 -> #REF! | M112: P | N112: Q | O112: Total
B113: Delegates ID Card | C113: 1349 | D113: 323 | E113: =C113*D113 -> 435727 | F113: =G113 -> Delegates ID Card | G113: Delegates ID Card | H113: 955 | I113: 325 | J113: =H113*I113 -> 310375 | L113: Delegates ID Card | M113: 952 | N113: 330 | O113: =M113*N113 -> 314160
B114: Sugarcubes Envelope (100 pcs) | C114: 27660 | D114: 4 | E114: =C114*D114 -> 110640 | F114: =G114 -> Sugarcubes Envelope (100 pcs) | G114: Sugarcubes Envelope (100 pcs) | H114: 22500 | I114: 4 | J114: =H114*I114 -> 90000 | L114: Sugarcubes Envelope (100 pcs) | M114: 22000 | N114: 4 | O114: =M114*N114 -> 88000
B115: Delegates Kit | C115: 10000 | D115: 323 | E115: =C115*D115 -> 3230000 | F115: =G115 -> Delegates Kit | G115: Delegates Kit | H115: 8000 | I115: 325 | J115: =H115*I115 -> 2600000 | L115: Delegates Kit | M115: 5000 | N115: 330 | O115: =M115*N115 -> 1650000
B116: [Medicine] Mylanta | C116: 11681 | D116: 1 | E116: =C116*D116 -> 11681 | F116: =G116 -> [Medicine] Mylanta | G116: [Medicine] Mylanta | H116: 10700 | I116: 1 | J116: =H116*I116 -> 10700 | L116: [Medicine] Mylanta | M116: 10000 | N116: 1 | O116: =M116*N116 -> 10000
B117: [Medicine] Sanmol | C117: 4500 | D117: 4 | E117: =C117*D117 -> 18000 | F117: =G117 -> [Medicine] Sanmol | G117: [Medicine] Sanmol | H117: 2500 | I117: 4 | J117: =H117*I117 -> 10000 | L117: [Medicine] Sanmol | M117: 2000 | N117: 4 | O117: =M117*N117 -> 8000
B118: [Medicine] Tolak Angin | C118: 63700 | D118: 1 | E118: =C118*D118 -> 63700 | F118: =G118 -> [Medicine] Tolak Angin | G118: [Medicine] Tolak Angin | H118: 57950 | I118: 1 | J118: =H118*I118 -> 57950 | L118: [Medicine] Tolak Angin | M118: 55000 | N118: 1 | O118: =M118*N118 -> 55000
B119: [Medicine] Minyak Kayu Putih (S) | C119: 16600 | D119: 1 | E119: =C119*D119 -> 16600 | F119: =G119 -> [Medicine] Minyak Kayu Putih (S) | G119: [Medicine] Minyak Kayu Putih (S) | H119: 14000 | I119: 1 | J119: =H119*I119 -> 14000 | L119: [Medicine] Minyak Kayu Putih (S) | M119: 13794 | N119: 1 | O119: =M119*N119 -> 13794
B120: [Medicine] Decolgen FX | C120: 15300 | D120: 1 | E120: =C120*D120 -> 15300 | F120: =G120 -> [Medicine] Decolgen FX | G120: [Medicine] Decolgen FX | H120: 15200 | I120: 1 | J120: =H120*I120 -> 15200 | L120: [Medicine] Decolgen FX | M120: 13800 | N120: 1 | O120: =M120*N120 -> 13800
B121: [Medicine] Hansaplast | C121: 15500 | D121: 2 | E121: =C121*D121 -> 31000 | F121: =G121 -> [Medicine] Hansaplast | G121: [Medicine] Hansaplast | H121: 11572 | I121: 2 | J121: =H121*I121 -> 23144 | L121: [Medicine] Hansaplast | M121: 10900 | N121: 2 | O121: =M121*N121 -> 21800
B122: [Medicine] Betadine (S) | C122: 24150 | D122: 1 | E122: =C122*D122 -> 24150 | G122: [Medicine] Betadine (S) | H122: 20778 | I122: 1 | J122: =H122*I122 -> 20778 | L122: [Medicine] Betadine (S) | M122: 18663 | N122: 1 | O122: =M122*N122 -> 18663
B123: [Medicine] Kain Kassa | C123: 10000 | D123: 1 | E123: =C123*D123 -> 10000 | G123: [Medicine] Kain Kassa | H123: 9257 | I123: 1 | J123: =H123*I123 -> 9257 | L123: [Medicine] Kain Kassa | M123: 8500 | N123: 1 | O123: =M123*N123 -> 8500
B124: [Medicine] Hansaplast Plester Roll | C124: 15895 | D124: 1 | E124: =C124*D124 -> 15895 | G124: [Medicine] Hansaplast Plester Roll | H124: 15043 | I124: 1 | J124: =H124*I124 -> 15043 | L124: [Medicine] Hansaplast Plester Roll | M124: 14690 | N124: 1 | O124: =M124*N124 -> 14690
B125: [Medicine] Pads / Pembalut | C125: 31510 | D125: 2 | E125: =C125*D125 -> 63020 | G125: [Medicine] Pads / Pembalut | H125: 29000 | I125: 2 | J125: =H125*I125 -> 58000 | L125: [Medicine] Pads / Pembalut | M125: 28400 | N125: 2 | O125: =M125*N125 -> 56800
B126: Double Tape | C126: 8500 | D126: 5 | E126: =C126*D126 -> 42500 | G126: Double Tape | H126: 6125 | I126: 5 | J126: =H126*I126 -> 30625 | L126: Double Tape | M126: 6000 | N126: 5 | O126: =M126*N126 -> 30000
B127: Print Foto + Nama Delegates | C127: 3000 | D127: 40 | E127: =C127*D127 -> 120000 | G127: Print Foto + Nama Delegates | H127: 2000 | I127: 45 | J127: =H127*I127 -> 90000 | L127: Print Foto + Nama Delegates | M127: 1500 | N127: 50 | O127: =M127*N127 -> 75000
B128: Print Nametag Delegates | C128: 3000 | D128: 80 | E128: =C128*D128 -> 240000 | G128: Print Nametag Delegates | H128: 2000 | I128: 82 | J128: =H128*I128 -> 164000 | L128: Print Nametag Delegates | M128: 1500 | N128: 85 | O128: =M128*N128 -> 127500
B129: Stickers RnR | C129: 6000 | D129: 3 | E129: =C129*D129 -> 18000 | G129: Stickers RnR | H129: 5000 | I129: 3 | J129: =H129*I129 -> 15000 | L129: Stickers RnR | M129: 4000 | N129: 3 | O129: =M129*N129 -> 12000
B130: RnR Certificate | C130: 12000 | D130: 3 | E130: =C130*D130 -> 36000 | G130: RnR Certificate | H130: 10000 | I130: 3 | J130: =H130*I130 -> 30000 | L130: RnR Certificate | M130: 8000 | N130: 3 | O130: =M130*N130 -> 24000
...

Sheet with VIDEOTRON💰BUDGET PLAN💰
B1: =CONCATENATE('🏦COVER🏦'!D7," 💰Budget Plan💰") -> #REF!
B2: 💔Pessimistic Plan💔 | G2: 🤍Realistic Plan🤍 | L2: 💗Optimistic Plan💗
B3: REVENUE BREAKDOWN | G3: REVENUE BREAKDOWN | L3: REVENUE BREAKDOWN
B4: (revenue stream) | C4: P | D4: Q | E4: Total | G4: (revenue stream) | H4: P | I4: Q | J4: Total | L4: (revenue stream) | M4: P | N4: Q | O4: Total
B5: Delegates Fee | C5: 1100000 | D5: 320 | E5: =C5*D5 -> 352000000 | G5: Delegates Fee | H5: 1100000 | I5: 320 | J5: =H5*I5 -> 352000000 | L5: Delegates Fee | M5: 1100000 | N5: 320 | O5: =M5*N5 -> 352000000
B6: International Delegates Fee | C6: 1500000 | D6: 3 | E6: =C6*D6 -> 4500000 | G6: International Delegates Fee | H6: 1500000 | I6: 5 | J6: =H6*I6 -> 7500000 | L6: International Delegates Fee | M6: 1500000 | N6: 10 | O6: =M6*N6 -> 15000000
B7: Commitment Fee | C7: 50000 | D7: 323 | E7: =C7*D7 -> 16150000 | G7: Commitment Fee | H7: 50000 | I7: 325 | J7: =H7*I7 -> 16250000 | L7: Commitment Fee | M7: 50000 | N7: 330 | O7: =M7*N7 -> 16500000
B8: Working Capital from MC | C8: 40000000 | D8: 1 | E8: =C8*D8 -> 40000000 | G8: Working Capital from MC | H8: 40000000 | I8: 1 | J8: =H8*I8 -> 40000000 | L8: Working Capital from MC | M8: 40000000 | N8: 1 | O8: =M8*N8 -> 40000000
B9: Working Capital from LC | C9: 5000000 | D9: 1 | E9: =C9*D9 -> 5000000 | G9: Working Capital from LC | H9: 5000000 | I9: 1 | J9: =H9*I9 -> 5000000 | L9: Working Capital from LC | M9: 5000000 | N9: 1 | O9: =M9*N9 -> 5000000
B10: [Merchandise] Baseball Cap | C10: 65000 | D10: 5 | E10: =C10*D10 -> 325000 | G10: [Merchandise] Baseball Cap | H10: 65000 | I10: 10 | J10: =H10*I10 -> 650000 | L10: [Merchandise] Baseball Cap | M10: 65000 | N10: 15 | O10: =M10*N10 -> 975000
B11: [Merchandise] Baseball Shirt | C11: 165000 | D11: 5 | E11: =C11*D11 -> 825000 | G11: [Merchandise] Baseball Shirt | H11: 165000 | I11: 10 | J11: =H11*I11 -> 1650000 | L11: [Merchandise] Baseball Shirt | M11: 165000 | N11: 15 | O11: =M11*N11 -> 2475000
B12: [Merchandise] T-Shirt | C12: 120000 | D12: 5 | E12: =C12*D12 -> 600000 | G12: [Merchandise] T-Shirt | H12: 120000 | I12: 10 | J12: =H12*I12 -> 1200000 | L12: [Merchandise] T-Shirt | M12: 120000 | N12: 15 | O12: =M12*N12 -> 1800000
B13: [Merchandise] Stickers | C13: 12000 | D13: 20 | E13: =C13*D13 -> 240000 | G13: [Merchandise] Stickers | H13: 12000 | I13: 25 | J13: =H13*I13 -> 300000 | L13: [Merchandise] Stickers | M13: 12000 | N13: 35 | O13: =M13*N13 -> 420000
B14: [Merchandise] Blind Box Keychain | C14: 20000 | D14: 15 | E14: =C14*D14 -> 300000 | G14: [Merchandise] Blind Box Keychain | H14: 20000 | I14: 25 | J14: =H14*I14 -> 500000 | L14: [Merchandise] Blind Box Keychain | M14: 20000 | N14: 35 | O14: =M14*N14 -> 700000
B15: [Merchandise] Keychain AIESEC | C15: 15000 | D15: 5 | E15: =C15*D15 -> 75000 | G15: [Merchandise] Keychain AIESEC | H15: 15000 | I15: 10 | J15: =H15*I15 -> 150000 | L15: [Merchandise] Keychain AIESEC | M15: 15000 | N15: 15 | O15: =M15*N15 -> 225000
B16: [Merchandise] Button Pins | C16: 15000 | D16: 15 | E16: =C16*D16 -> 225000 | G16: [Merchandise] Button Pins | H16: 15000 | I16: 25 | J16: =H16*I16 -> 375000 | L16: [Merchandise] Button Pins | M16: 15000 | N16: 35 | O16: =M16*N16 -> 525000
... B26: Baju CDT | C26: 80000 | D26: 39 | E26: =C26*D26 -> 3120000 | G26: Baju CDT | H26: 80000 | I26: 39 | J26: =H26*I26 -> 3120000 | L26: Baju CDT | M26: 80000 | N26: 39 | O26: =M26*N26 -> 3120000
B27: TOTAL REVENUE | E27: =SUM(E5:E10) -> 417975000 | G27: TOTAL REVENUE | J27: =SUM(J5:J10) -> 421400000 | L27: TOTAL REVENUE | O27: =SUM(O5:O10) -> 429475000
B29: Expenses | E29: Total | G29: Expenses | J29: Total | L29: Expenses | O29: Total
B30: =$B$40 -> #REF! | E30: =E79 -> 31112608 | G30: =B30 -> #REF! | J30: =J79 -> 33496933 | L30: =G30 -> #REF! | O30: =O79 -> 34598876
B31: =B81 -> #REF! | E31: =E110 -> 2060700 | G31: =B31 -> #REF! | J31: =J110 -> 1340798 | L31: =G31 -> #REF! | O31: =O110 -> 940036
B32: =B112 -> #REF! | E32: =E132 -> 6267213 | G32: =B32 -> #REF! | J32: =J132 -> 4334072 | L32: =G32 -> #REF! | O32: =O132 -> 2631707
B33: =B134 -> #REF! | E33: =E147 -> 1673000 | G33: =B33 -> #REF! | J33: =J147 -> 1408000 | L33: =G33 -> #REF! | O33: =O147 -> 1111000
B34: =B149 -> #REF! | E34: =E160 -> 2120000 | G34: =B34 -> #REF! | J34: =J160 -> 1652320 | L34: =G34 -> #REF! | O34: =O160 -> 1464000
B35: =B162 -> #REF! | E35: =E174 -> 390905200 | G35: =B35 -> #REF! | J35: =J174 -> 381261745 | L35: =G35 -> #REF! | O35: =O174 -> 378914100
B36: TOTAL EXPENSES | E36: =SUM(E30:E35) -> 434138721 | G36: TOTAL EXPENSES | J36: =SUM(J30:J35) -> 423493868 | L36: TOTAL EXPENSES | O36: =SUM(O30:O35) -> 419659719
B37: NET PROFIT | E37: =E27-E36 -> -16163721 | G37: NET PROFIT | J37: =J27-J36 -> -2093868 | L37: NET PROFIT | O37: =O27-O36 -> 9815281
B39: EXPENSE BREAKDOWN | G39: EXPENSE BREAKDOWN | L39: EXPENSE BREAKDOWN
B40: ='🏦COVER🏦'!D11 -> #REF! | C40: P | D40: Q | E40: Total | G40: =B40 -> #REF! | H40: P | I40: Q | J40: Total | L40: =G40 -> #REF! | M40: P | N40: Q | O40: Total
B41: Lanyard CDT | C41: 15000 | D41: 39 | E41: =C41*D41 -> 585000 | F41: =G41 -> Lanyard CDT | G41: Lanyard CDT | H41: 10000 | I41: 39 | J41: =H41*I41 -> 390000 | L41: Lanyard CDT | M41: 9000 | N41: 39 | O41: =M41*N41 -> 351000
B42: Baju CDT | C42: 80000 | D42: 39 | E42: =C42*D42 -> 3120000 | F42: =G42 -> Baju CDT | G42: Baju CDT | H42: 80000 | I42: 39 | J42: =H42*I42 -> 3120000 | L42: Baju CDT | M42: 80000 | N42: 39 | O42: =M42*N42 -> 3120000
B43: Baju Coach + MC WLL | C43: 70000 | D43: 45 | E43: =C43*D43 -> 3150000 | G43: Baju Coach + MC WLL | H43: 70000 | I43: 45 | J43: =H43*I43 -> 3150000 | L43: Baju Coach + MC WLL | M43: 70000 | N43: 45 | O43: =M43*N43 -> 3150000
B44: [Merchandise] Baseball Cap | C44: 45000 | D44: 15 | E44: =C44*D44 -> 675000 | F44: =G44 -> [Merchandise] Baseball Cap | G44: [Merchandise] Baseball Cap | H44: 40000 | I44: 25 | J44: =H44*I44 -> 1000000 | L44: [Merchandise] Baseball Cap | M44: 35000 | N44: 35 | O44: =M44*N44 -> 1225000
B45: [Merchandise] Baseball Shirt | C45: 135000 | D45: 5 | E45: =C45*D45 -> 675000 | F45: =G45 -> [Merchandise] Baseball Shirt | G45: [Merchandise] Baseball Shirt | H45: 120000 | I45: 25 | J45: =H45*I45 -> 3000000 | L45: [Merchandise] Baseball Shirt | M45: 100000 | N45: 35 | O45: =M45*N45 -> 3500000
B46: [Merchandise] T-Shirt | C46: 85000 | D46: 5 | E46: =C46*D46 -> 425000 | G46: [Merchandise] T-Shirt | H46: 80000 | I46: 10 | J46: =H46*I46 -> 800000 | L46: [Merchandise] T-Shirt | M46: 70000 | N46: 15 | O46: =M46*N46 -> 1050000
B47: [Merchandise] Button Pins | C47: 6000 | D47: 110 | E47: =C47*D47 -> 660000 | G47: [Merchandise] Button Pins | H47: 6000 | I47: 135 | J47: =H47*I47 -> 810000 | L47: [Merchandise] Button Pins | M47: 6000 | N47: 160 | O47: =M47*N47 -> 960000
B48: [Merchandise] Blind Box Keychain | C48: 8000 | D48: 110 | E48: =C48*D48 -> 880000 | G48: [Merchandise] Blind Box Keychain | H48: 7000 | I48: 135 | J48: =H48*I48 -> 945000 | L48: [Merchandise] Blind Box Keychain | M48: 6500 | N48: 160 | O48: =M48*N48 -> 1040000
B49: [Merchandise] Keychain | C49: 7000 | D49: 5 | E49: =C49*D49 -> 35000 | G49: [Merchandise] Keychain | H49: 6000 | I49: 10 | J49: =H49*I49 -> 60000 | L49: [Merchandise] Keychain | M49: 5000 | N49: 15 | O49: =M49*N49 -> 75000
B50: [Merchandise] Stickers | C50: 8000 | D50: 59 | E50: =C50*D50 -> 472000 | G50: [Merchandise] Stickers | H50: 5000 | I50: 70 | J50: =H50*I50 -> 350000 | L50: [Merchandise] Stickers | M50: 4000 | N50: 88 | O50: =M50*N50 -> 352000
B51: [CC Corner] Print Paper for Drawing Photobooth | C51: 10000 | D51: 5 | E51: =C51*D51 -> 50000 | G51: [CC Corner] Print Paper for Drawing Photobooth | H51: 7000 | I51: 7 | J51: =H51*I51 -> 49000 | L51: [CC Corner] Print Paper for Drawing Photobooth | M51: 5000 | N51: 10 | O51: =M51*N51 -> 50000
B52: [CC Corner] Drawing Marker | C52: 10000 | D52: 2 | E52: =C52*D52 -> 20000 | G52: [CC Corner] Drawing Marker | H52: 9000 | I52: 2 | J52: =H52*I52 -> 18000 | L52: [CC Corner] Drawing Marker | M52: 7000 | N52: 2 | O52: =M52*N52 -> 14000
B53: [CC Corner[ Yupi Hati | C53: 22999 | D53: 2 | E53: =C53*D53 -> 45998 | G53: [CC Corner[ Yupi Hati | H53: 22999 | I53: 3 | J53: =H53*I53 -> 68997 | L53: [CC Corner[ Yupi Hati | M53: 22999 | N53: 4 | O53: =M53*N53 -> 91996
B54: [CC Corner] Yupi | C54: 15000 | D54: 5 | E54: =C54*D54 -> 75000 | G54: [CC Corner] Yupi | H54: 14000 | I54: 8 | J54: =H54*I54 -> 112000 | L54: [CC Corner] Yupi | M54: 12700 | N54: 10 | O54: =M54*N54 -> 127000
B55: [CC Corner] Beng Beng 17g | C55: 44200 | D55: 5 | E55: =C55*D55 -> 221000 | G55: [CC Corner] Beng Beng 17g | H55: 43500 | I55: 5 | J55: =H55*I55 -> 217500 | L55: [CC Corner] Beng Beng 17g | M55: 37600 | N55: 5 | O55: =M55*N55 -> 188000
B56: [CC Corner] Astor Singles 14g | C56: 22000 | D56: 5 | E56: =C56*D56 -> 110000 | G56: [CC Corner] Astor Singles 14g | H56: 20600 | I56: 7 | J56: =H56*I56 -> 144200 | L56: [CC Corner] Astor Singles 14g | M56: 18800 | N56: 10 | O56: =M56*N56 -> 188000
B57: [CC Corner] Permen Relaxa | C57: 8250 | D57: 5 | E57: =C57*D57 -> 41250 | G57: [CC Corner] Permen Relaxa | H57: 8000 | I57: 5 | J57: =H57*I57 -> 40000 | L57: [CC Corner] Permen Relaxa | M57: 6700 | N57: 5 | O57: =M57*N57 -> 33500
... B71: Emergency Cost | C71: 3000000 | D71: 1 | E71: =C71*D71 -> 3000000 | G71: Emergency Cost | H71: 2000000 | I71: 1 | J71: =H71*I71 -> 2000000 | L71: Emergency Cost | M71: 1500000 | N71: 1 | O71: =M71*N71 -> 1500000
B72: =G72 | E72: 0 | F72: =G72 | J72: =H72*I72 -> 0 | L72: =G72 | O72: 0
B73: =G73 | E73: 0 | F73: =G73 | J73: =H73*I73 -> 0 | L73: =G73 | O73: 0
B74: =G74 | E74: 0 | F74: =G74 | J74: =H74*I74 -> 0 | L74: =G74 | O74: 0
B75: =G75 | E75: 0 | F75: =G75 | J75: =H75*I75 -> 0 | L75: =G75 | O75: 0
B76: =G76 | E76: 0 | F76: =G76 | J76: =H76*I76 -> 0 | L76: =G76 | O76: 0
B77: =G77 | E77: 0 | F77: =G77 | J77: =H77*I77 -> 0 | L77: =G77 | O77: 0
B78: =G78 | E78: 0 | F78: =G78 | J78: =H78*I78 -> 0 | L78: =G78 | O78: 0
B79: TOTAL EXPENSE | E79: =SUM(E41:E78) -> 31112608 | G79: TOTAL EXPENSE | J79: =SUM(J41:J78) -> 33496933 | L79: TOTAL EXPENSE | O79: =SUM(O41:O78) -> 34598876
B81: ='🏦COVER🏦'!D12 -> #REF! | C81: P | D81: Q | E81: Total | G81: =B81 -> #REF! | H81: P | I81: Q | J81: Total | L81: =B81 -> #REF! | M81: P | N81: Q | O81: Total
B82: [CC Party] Amplop putih kecil | C82: 13000 | D82: 2 | E82: =C82*D82 -> 26000 | F82: =G82 -> [CC Party] Amplop putih kecil | G82: [CC Party] Amplop putih kecil | H82: 5150 | I82: 3 | J82: =H82*I82 -> 15450 | L82: [CC Party] Amplop putih kecil | M82: 4500 | N82: 3 | O82: =M82*N82 -> 13500
B83: [CC Party] Print puzzle (kertas karton) | C83: 17000 | D83: 5 | E83: =C83*D83 -> 85000 | F83: =G83 -> [CC Party] Print puzzle (kertas karton) | G83: [CC Party] Print puzzle (kertas karton) | H83: 15000 | I83: 5 | J83: =H83*I83 -> 75000 | L83: [CC Party] Print puzzle (kertas karton) | M83: 10000 | N83: 5 | O83: =M83*N83 -> 50000
B84: [CC Party] print card makanan | C84: 2000 | D84: 20 | E84: =C84*D84 -> 40000 | F84: =G84 -> [CC Party] print card makanan | G84: [CC Party] print card makanan | H84: 1500 | I84: 20 | J84: =H84*I84 -> 30000 | L84: [CC Party] print card makanan | M84: 1000 | N84: 20 | O84: =M84*N84 -> 20000
B85: [CC Party] Jahe | C85: 8000 | D85: 1 | E85: =C85*D85 -> 8000 | F85: =G85 -> [CC Party] Jahe | G85: [CC Party] Jahe | H85: 7000 | I85: 1 | J85: =H85*I85 -> 7000 | L85: [CC Party] Jahe | M85: 5000 | N85: 1 | O85: =M85*N85 -> 5000
B86: [CC Party] Kunyit | C86: 8000 | D86: 1 | E86: =C86*D86 -> 8000 | F86: =G86 -> [CC Party] Kunyit | G86: [CC Party] Kunyit | H86: 7000 | I86: 1 | J86: =H86*I86 -> 7000 | L86: [CC Party] Kunyit | M86: 5000 | N86: 1 | O86: =M86*N86 -> 5000
B87: [CC Party] Lengkuas/Laos | C87: 8000 | D87: 1 | E87: =C87*D87 -> 8000 | F87: =G87 -> [CC Party] Lengkuas/Laos | G87: [CC Party] Lengkuas/Laos | H87: 7000 | I87: 1 | J87: =H87*I87 -> 7000 | L87: [CC Party] Lengkuas/Laos | M87: 5000 | N87: 1 | O87: =M87*N87 -> 5000
B88: [CC Party] Kencur | C88: 10000 | D88: 1 | E88: =C88*D88 -> 10000 | F88: =G88 -> CC Party] Kencur | G88: CC Party] Kencur | H88: 8000 | I88: 1 | J88: =H88*I88 -> 8000 | L88: CC Party] Kencur | M88: 5000 | N88: 1 | O88: =M88*N88 -> 5000
B89: [CC Party] Serai/Sereh | C89: 8000 | D89: 1 | E89: =C89*D89 -> 8000 | F89: =G89 -> [CC Party] Serai/Sereh | G89: [CC Party] Serai/Sereh | H89: 7000 | I89: 1 | J89: =H89*I89 -> 7000 | L89: [CC Party] Serai/Sereh | M89: 5000 | N89: 1 | O89: =M89*N89 -> 5000
B90: [CC Party] Daun Jeruk | C90: 7500 | D90: 1 | E90: =C90*D90 -> 7500 | G90: CC Party] Daun Jeruk | H90: 5000 | I90: 1 | J90: =H90*I90 -> 5000 | L90: CC Party] Daun Jeruk | M90: 3000 | N90: 1 | O90: =M90*N90 -> 3000
B91: [CC Party] Kayu manis | C91: 20000 | D91: 1 | E91: =C91*D91 -> 20000 | F91: =G91 -> CC Party] Kayu manis | G91: CC Party] Kayu manis | H91: 15000 | I91: 1 | J91: =H91*I91 -> 15000 | L91: CC Party] Kayu manis | M91: 10000 | N91: 1 | O91: =M91*N91 -> 10000
B92: [CC Party] Ketumbar | C92: 7500 | D92: 1 | E92: =C92*D92 -> 7500 | G92: CC Party] Ketumbar | H92: 6000 | I92: 1 | J92: =H92*I92 -> 6000 | L92: CC Party] Ketumbar | M92: 4000 | N92: 1 | O92: =M92*N92 -> 4000
B93: [CC Party] Cengkeh | C93: 9000 | D93: 1 | E93: =C93*D93 -> 9000 | G93: CC Party] Cengkeh | H93: 7000 | I93: 1 | J93: =H93*I93 -> 7000 | L93: CC Party] Cengkeh | M93: 4000 | N93: 1 | O93: =M93*N93 -> 4000
B94: [CC Party] Kemiri | C94: 7000 | D94: 1 | E94: =C94*D94 -> 7000 | G94: CC Party] Kemiri | H94: 5000 | I94: 1 | J94: =H94*I94 -> 5000 | L94: CC Party] Kemiri | M94: 3000 | N94: 1 | O94: =M94*N94 -> 3000
B95: [CC Party] Sertificate RnR | C95: 5000 | D95: 4 | E95: =C95*D95 -> 20000 | G95: CC Party] Sertificate RnR | H95: 4000 | I95: 4 | J95: =H95*I95 -> 16000 | L95: CC Party] Sertificate RnR | M95: 3000 | N95: 4 | O95: =M95*N95 -> 12000
B96: [CC Party] Gift RnR | C96: 65000 | D96: 4 | E96: =C96*D96 -> 260000 | G96: [CC Party] Gift RnR | H96: 50000 | I96: 4 | J96: =H96*I96 -> 200000 | L96: [CC Party] Gift RnR | M96: 40000 | N96: 4 | O96: =M96*N96 -> 160000
B97: [FACI Needs] | C97: 700000 | D97: 1 | E97: =C97*D97 -> 700000 | G97: [FACI Needs] | H97: 500000 | I97: 1 | J97: =H97*I97 -> 500000 | L97: [FACI Needs] | M97: 400000 | N97: 1 | O97: =M97*N97 -> 400000
B98: Print Cover Cue Card + Laminating | C98: 5000 | D98: 2 | E98: =C98*D98 -> 10000 | G98: Print Cover Cue Card + Laminating | H98: 4000 | I98: 2 | J98: =H98*I98 -> 8000 | L98: Print Cover Cue Card + Laminating | M98: 3000 | N98: 2 | O98: =M98*N98 -> 6000
B99: [WLL] Karton A1 | C99: 10000 | D99: 4 | E99: =C99*D99 -> 40000 | G99: [WLL] Karton A1 | H99: 8000 | I99: 3 | J99: =H99*I99 -> 24000 | L99: [WLL] Karton A1 | M99: 6500 | N99: 2 | O99: =M99*N99 -> 13000
B100: [WLL] Cat Warna Pink 100ml | C100: 11000 | D100: 4 | E100: =C100*D100 -> 44000 | G100: [WLL] Cat Warna Pink 100ml | H100: 11000 | I100: 3 | J100: =H100*I100 -> 33000 | L100: [WLL] Cat Warna Pink 100ml | M100: 11000 | N100: 2 | O100: =M100*N100 -> 22000
B101: [WLL] Cat Warna Kuning 100ml | C101: 11000 | D101: 4 | E101: =C101*D101 -> 44000 | G101: [WLL] Cat Warna Kuning 100ml | H101: 11000 | I101: 3 | J101: =H101*I101 -> 33000 | L101: [WLL] Cat Warna Kuning 100ml | M101: 11000 | N101: 2 | O101: =M101*N101 -> 22000
B102: [WLL] Cat Warna Hijau 100ml | C102: 11000 | D102: 4 | E102: =C102*D102 -> 44000 | G102: [WLL] Cat Warna Hijau 100ml | H102: 11000 | I102: 3 | J102: =H102*I102 -> 33000 | L102: [WLL] Cat Warna Hijau 100ml | M102: 11000 | N102: 2 | O102: =M102*N102 -> 22000
B103: [WLL] Cat Warna Biru Muda 100ml | C103: 11000 | D103: 4 | E103: =C103*D103 -> 44000 | G103: [WLL] Cat Warna Biru Muda 100ml | H103: 11000 | I103: 3 | J103: =H103*I103 -> 33000 | L103: [WLL] Cat Warna Biru Muda 100ml | M103: 11000 | N103: 2 | O103: =M103*N103 -> 22000
... B108: [Global Village] Print Stamp Card Custom | C108: 500 | D108: 323 | E108: =C108*D108 -> 161500 | G108: [Global Village] Print Stamp Card Custom | H108: 300 | I108: 325 | J108: =H108*I108 -> 97500 | L108: [Global Village] Print Stamp Card Custom | M108: 150 | N108: 330 | O108: =M108*N108 -> 49500
B109: Printing Placard NLF & NLM | C109: 50000 | D109: 1 | E109: =C109*D109 -> 50000 | F109: =G109 -> Printing Placard NLF & NLM | G109: Printing Placard NLF & NLM | H109: 40000 | I109: 1 | J109: =H109*I109 -> 40000 | L109: Printing Placard NLF & NLM | M109: 35000 | N109: 1 | O109: =M109*N109 -> 35000
B110: TOTAL EXPENSE | E110: =SUM(E82:E109) -> 2060700 | F110: [Program] Logistics | G110: TOTAL EXPENSE | J110: =SUM(J85:J109) -> 1340798 | L110: TOTAL EXPENSE | O110: =SUM(O85:O109) -> 940036
B112: ='🏦COVER🏦'!D13 -> #REF! | C112: P | D112: Q | E112: Total | G112: =B112 -> #REF! | H112: P | I112: Q | J112: Total | L112: =B112 -> #REF! | M112: P | N112: Q | O112: Total
B113: Delegates ID Card | C113: 1349 | D113: 323 | E113: =C113*D113 -> 435727 | F113: =G113 -> Delegates ID Card | G113: Delegates ID Card | H113: 955 | I113: 325 | J113: =H113*I113 -> 310375 | L113: Delegates ID Card | M113: 952 | N113: 330 | O113: =M113*N113 -> 314160
B114: Sugarcubes Envelope (100 pcs) | C114: 27660 | D114: 4 | E114: =C114*D114 -> 110640 | F114: =G114 -> Sugarcubes Envelope (100 pcs) | G114: Sugarcubes Envelope (100 pcs) | H114: 22500 | I114: 4 | J114: =H114*I114 -> 90000 | L114: Sugarcubes Envelope (100 pcs) | M114: 22000 | N114: 4 | O114: =M114*N114 -> 88000
B115: Delegates Kit | C115: 15000 | D115: 323 | E115: =C115*D115 -> 4845000 | F115: =G115 -> Delegates Kit | G115: Delegates Kit | H115: 10000 | I115: 325 | J115: =H115*I115 -> 3250000 | L115: Delegates Kit | M115: 5000 | N115: 330 | O115: =M115*N115 -> 1650000
B116: [Medicine] Mylanta | C116: 11681 | D116: 1 | E116: =C116*D116 -> 11681 | F116: =G116 -> [Medicine] Mylanta | G116: [Medicine] Mylanta | H116: 10700 | I116: 1 | J116: =H116*I116 -> 10700 | L116: [Medicine] Mylanta | M116: 10000 | N116: 1 | O116: =M116*N116 -> 10000
B117: [Medicine] Sanmol | C117: 4500 | D117: 4 | E117: =C117*D117 -> 18000 | F117: =G117 -> [Medicine] Sanmol | G117: [Medicine] Sanmol | H117: 2500 | I117: 4 | J117: =H117*I117 -> 10000 | L117: [Medicine] Sanmol | M117: 2000 | N117: 4 | O117: =M117*N117 -> 8000
B118: [Medicine] Tolak Angin | C118: 63700 | D118: 1 | E118: =C118*D118 -> 63700 | F118: =G118 -> [Medicine] Tolak Angin | G118: [Medicine] Tolak Angin | H118: 57950 | I118: 1 | J118: =H118*I118 -> 57950 | L118: [Medicine] Tolak Angin | M118: 55000 | N118: 1 | O118: =M118*N118 -> 55000
B119: [Medicine] Minyak Kayu Putih (S) | C119: 16600 | D119: 1 | E119: =C119*D119 -> 16600 | F119: =G119 -> [Medicine] Minyak Kayu Putih (S) | G119: [Medicine] Minyak Kayu Putih (S) | H119: 14000 | I119: 1 | J119: =H119*I119 -> 14000 | L119: [Medicine] Minyak Kayu Putih (S) | M119: 13794 | N119: 1 | O119: =M119*N119 -> 13794
B120: [Medicine] Decolgen FX | C120: 15300 | D120: 1 | E120: =C120*D120 -> 15300 | F120: =G120 -> [Medicine] Decolgen FX | G120: [Medicine] Decolgen FX | H120: 15200 | I120: 1 | J120: =H120*I120 -> 15200 | L120: [Medicine] Decolgen FX | M120: 13800 | N120: 1 | O120: =M120*N120 -> 13800
B121: [Medicine] Hansaplast | C121: 15500 | D121: 2 | E121: =C121*D121 -> 31000 | F121: =G121 -> [Medicine] Hansaplast | G121: [Medicine] Hansaplast | H121: 11572 | I121: 2 | J121: =H121*I121 -> 23144 | L121: [Medicine] Hansaplast | M121: 10900 | N121: 2 | O121: =M121*N121 -> 21800
B122: [Medicine] Betadine (S) | C122: 24150 | D122: 1 | E122: =C122*D122 -> 24150 | G122: [Medicine] Betadine (S) | H122: 20778 | I122: 1 | J122: =H122*I122 -> 20778 | L122: [Medicine] Betadine (S) | M122: 18663 | N122: 1 | O122: =M122*N122 -> 18663
B123: [Medicine] Kain Kassa | C123: 10000 | D123: 1 | E123: =C123*D123 -> 10000 | G123: [Medicine] Kain Kassa | H123: 9257 | I123: 1 | J123: =H123*I123 -> 9257 | L123: [Medicine] Kain Kassa | M123: 8500 | N123: 1 | O123: =M123*N123 -> 8500
B124: [Medicine] Hansaplast Plester Roll | C124: 15895 | D124: 1 | E124: =C124*D124 -> 15895 | G124: [Medicine] Hansaplast Plester Roll | H124: 15043 | I124: 1 | J124: =H124*I124 -> 15043 | L124: [Medicine] Hansaplast Plester Roll | M124: 14690 | N124: 1 | O124: =M124*N124 -> 14690
B125: [Medicine] Pads / Pembalut | C125: 31510 | D125: 2 | E125: =C125*D125 -> 63020 | G125: [Medicine] Pads / Pembalut | H125: 29000 | I125: 2 | J125: =H125*I125 -> 58000 | L125: [Medicine] Pads / Pembalut | M125: 28400 | N125: 2 | O125: =M125*N125 -> 56800
B126: Double Tape | C126: 8500 | D126: 5 | E126: =C126*D126 -> 42500 | G126: Double Tape | H126: 6125 | I126: 5 | J126: =H126*I126 -> 30625 | L126: Double Tape | M126: 6000 | N126: 5 | O126: =M126*N126 -> 30000
B127: Print Foto + Nama Delegates | C127: 3000 | D127: 40 | E127: =C127*D127 -> 120000 | G127: Print Foto + Nama Delegates | H127: 2000 | I127: 45 | J127: =H127*I127 -> 90000 | L127: Print Foto + Nama Delegates | M127: 1500 | N127: 50 | O127: =M127*N127 -> 75000
B128: Print Nametag Delegates | C128: 3000 | D128: 80 | E128: =C128*D128 -> 240000 | G128: Print Nametag Delegates | H128: 2000 | I128: 82 | J128: =H128*I128 -> 164000 | L128: Print Nametag Delegates | M128: 1500 | N128: 85 | O128: =M128*N128 -> 127500
B129: Stickers RnR | C129: 6000 | D129: 3 | E129: =C129*D129 -> 18000 | G129: Stickers RnR | H129: 5000 | I129: 3 | J129: =H129*I129 -> 15000 | L129: Stickers RnR | M129: 4000 | N129: 3 | O129: =M129*N129 -> 12000
B130: RnR Certificate | C130: 12000 | D130: 3 | E130: =C130*D130 -> 36000 | G130: RnR Certificate | H130: 10000 | I130: 3 | J130: =H130*I130 -> 30000 | L130: RnR Certificate | M130: 8000 | N130: 3 | O130: =M130*N130 -> 24000
...

Sheet 💰BUDGET PLAN💰
B1: 💰Budget Plan💰
B2: Pessimistic Plan | G2: Moderate Plan | L2: Optimistic Plan
B3: REVENUE BREAKDOWN | G3: REVENUE BREAKDOWN | L3: REVENUE BREAKDOWN
B4: (revenue stream) | C4: P | D4: Q | E4: Total | G4: (revenue stream) | H4: P | I4: Q | J4: Total | L4: (revenue stream) | M4: P | N4: Q | O4: Total
E5: =C5*D5 -> 0 | J5: =H5*I5 -> 0 | O5: =M5*N5 -> 0
E6: =C6*D6 -> 0 | J6: =H6*I6 -> 0 | O6: =M6*N6 -> 0
E7: =C7*D7 -> 0 | J7: =H7*I7 -> 0 | O7: =M7*N7 -> 0
E8: =C8*D8 -> 0 | J8: =H8*I8 -> 0 | O8: =M8*N8 -> 0
E9: =C9*D9 -> 0 | J9: =H9*I9 -> 0 | O9: =M9*N9 -> 0
E10: =C10*D10 -> 0 | J10: =H10*I10 -> 0 | O10: =M10*N10 -> 0
E11: =C11*D11 -> 0 | J11: =H11*I11 -> 0 | O11: =M11*N11 -> 0
E12: =C12*D12 -> 0 | J12: =H12*I12 -> 0 | O12: =M12*N12 -> 0
E13: =C13*D13 -> 0 | J13: =H13*I13 -> 0 | O13: =M13*N13 -> 0
E14: =C14*D14 -> 0 | J14: =H14*I14 -> 0 | O14: =M14*N14 -> 0
E15: =C15*D15 -> 0 | J15: =H15*I15 -> 0 | O15: =M15*N15 -> 0
E16: =C16*D16 -> 0 | J16: =H16*I16 -> 0 | O16: =M16*N16 -> 0
... E26: =C26*D26 -> 0 | J26: =H26*I26 -> 0 | O26: =M26*N26 -> 0
B27: TOTAL REVENUE | E27: =SUM(E5:E10) -> 0 | G27: TOTAL REVENUE | J27: =SUM(J5:J10) -> 0 | L27: TOTAL REVENUE | O27: =SUM(O5:O10) -> 0
B29: Expenses | E29: Total | G29: Expenses | J29: Total | L29: Expenses | O29: Total
B30: =$B$40 -> DIVISI A | E30: =E77 -> 0 | G30: =B30 -> DIVISI A | J30: =J77 -> 0 | L30: =G30 -> DIVISI A | O30: =O77 -> 0
B31: =B79 -> #REF! | E31: =E108 -> 0 | G31: =B31 -> #REF! | J31: =J108 -> 0 | L31: =G31 -> #REF! | O31: =O108 -> 0
B32: =B110 -> #REF! | E32: =E130 -> 0 | G32: =B32 -> #REF! | J32: =J130 -> 0 | L32: =G32 -> #REF! | O32: =O130 -> 0
B33: =B132 -> #REF! | E33: =E145 -> 0 | G33: =B33 -> #REF! | J33: =J145 -> 0 | L33: =G33 -> #REF! | O33: =O145 -> 0
B34: =B147 -> #REF! | E34: =E158 -> 0 | G34: =B34 -> #REF! | J34: =J158 -> 0 | L34: =G34 -> #REF! | O34: =O158 -> 0
B35: =B160 -> #REF! | E35: =E171 -> 0 | G35: =B35 -> #REF! | J35: =J171 -> 0 | L35: =G35 -> #REF! | O35: =O171 -> 0
B36: TOTAL EXPENSES | E36: =SUM(E30:E35) -> 0 | G36: TOTAL EXPENSES | J36: =SUM(J30:J35) -> 0 | L36: TOTAL EXPENSES | O36: =SUM(O30:O35) -> 0
B37: NET PROFIT | E37: =E27-E36 -> 0 | G37: NET PROFIT | J37: =J27-J36 -> 0 | L37: NET PROFIT | O37: =O27-O36 -> 0
B39: EXPENSE BREAKDOWN | G39: EXPENSE BREAKDOWN | L39: EXPENSE BREAKDOWN
B40: DIVISI A | C40: P | D40: Q | E40: Total | G40: =B40 -> DIVISI A | H40: P | I40: Q | J40: Total | L40: =G40 -> DIVISI A | M40: P | N40: Q | O40: Total
E41: =C41*D41 -> 0 | F41: =G41 | J41: =H41*I41 -> 0 | O41: =M41*N41 -> 0
E42: =C42*D42 -> 0 | F42: =G42 | J42: =H42*I42 -> 0 | O42: =M42*N42 -> 0
E43: =C43*D43 -> 0 | J43: =H43*I43 -> 0 | O43: =M43*N43 -> 0
E44: =C44*D44 -> 0 | F44: =G44 | J44: =H44*I44 -> 0 | O44: =M44*N44 -> 0
E45: =C45*D45 -> 0 | F45: =G45 | J45: =H45*I45 -> 0 | O45: =M45*N45 -> 0
E46: =C46*D46 -> 0 | J46: =H46*I46 -> 0 | O46: =M46*N46 -> 0
E47: =C47*D47 -> 0 | J47: =H47*I47 -> 0 | O47: =M47*N47 -> 0
E48: =C48*D48 -> 0 | J48: =H48*I48 -> 0 | O48: =M48*N48 -> 0
E49: =C49*D49 -> 0 | J49: =H49*I49 -> 0 | O49: =M49*N49 -> 0
E50: =C50*D50 -> 0 | J50: =H50*I50 -> 0 | O50: =M50*N50 -> 0
E51: =C51*D51 -> 0 | J51: =H51*I51 -> 0 | O51: =M51*N51 -> 0
E52: =C52*D52 -> 0 | J52: =H52*I52 -> 0 | O52: =M52*N52 -> 0
E53: =C53*D53 -> 0 | J53: =H53*I53 -> 0 | O53: =M53*N53 -> 0
E54: =C54*D54 -> 0 | J54: =H54*I54 -> 0 | O54: =M54*N54 -> 0
E55: =C55*D55 -> 0 | J55: =H55*I55 -> 0 | O55: =M55*N55 -> 0
E56: =C56*D56 -> 0 | J56: =H56*I56 -> 0 | O56: =M56*N56 -> 0
E57: =C57*D57 -> 0 | J57: =H57*I57 -> 0 | O57: =M57*N57 -> 0
... E69: =C69*D69 -> 0 | J69: =H69*I69 -> 0 | O69: =M69*N69 -> 0
B70: =G70 | E70: 0 | F70: =G70 | J70: =H70*I70 -> 0 | L70: =G70 | O70: 0
B71: =G71 | E71: 0 | F71: =G71 | J71: =H71*I71 -> 0 | L71: =G71 | O71: 0
B72: =G72 | E72: 0 | F72: =G72 | J72: =H72*I72 -> 0 | L72: =G72 | O72: 0
B73: =G73 | E73: 0 | F73: =G73 | J73: =H73*I73 -> 0 | L73: =G73 | O73: 0
B74: =G74 | E74: 0 | F74: =G74 | J74: =H74*I74 -> 0 | L74: =G74 | O74: 0
B75: =G75 | E75: 0 | F75: =G75 | J75: =H75*I75 -> 0 | L75: =G75 | O75: 0
B76: =G76 | E76: 0 | F76: =G76 | J76: =H76*I76 -> 0 | L76: =G76 | O76: 0
B77: TOTAL EXPENSE | E77: =SUM(E41:E76) -> 0 | G77: TOTAL EXPENSE | J77: =SUM(J41:J76) -> 0 | L77: TOTAL EXPENSE | O77: =SUM(O41:O76) -> 0
B79: ='🏦COVER🏦'!D12 -> #REF! | C79: P | D79: Q | E79: Total | G79: =B79 -> #REF! | H79: P | I79: Q | J79: Total | L79: =B79 -> #REF! | M79: P | N79: Q | O79: Total
E80: =C80*D80 -> 0 | F80: =G80 | J80: =H80*I80 -> 0 | O80: =M80*N80 -> 0
E81: =C81*D81 -> 0 | F81: =G81 | J81: =H81*I81 -> 0 | O81: =M81*N81 -> 0
E82: =C82*D82 -> 0 | F82: =G82 | J82: =H82*I82 -> 0 | O82: =M82*N82 -> 0
E83: =C83*D83 -> 0 | F83: =G83 | J83: =H83*I83 -> 0 | O83: =M83*N83 -> 0
E84: =C84*D84 -> 0 | F84: =G84 | J84: =H84*I84 -> 0 | O84: =M84*N84 -> 0
E85: =C85*D85 -> 0 | F85: =G85 | J85: =H85*I85 -> 0 | O85: =M85*N85 -> 0
E86: =C86*D86 -> 0 | F86: =G86 | J86: =H86*I86 -> 0 | O86: =M86*N86 -> 0
E87: =C87*D87 -> 0 | F87: =G87 | J87: =H87*I87 -> 0 | O87: =M87*N87 -> 0
E88: =C88*D88 -> 0 | J88: =H88*I88 -> 0 | O88: =M88*N88 -> 0
E89: =C89*D89 -> 0 | F89: =G89 | J89: =H89*I89 -> 0 | O89: =M89*N89 -> 0
E90: =C90*D90 -> 0 | J90: =H90*I90 -> 0 | O90: =M90*N90 -> 0
E91: =C91*D91 -> 0 | J91: =H91*I91 -> 0 | O91: =M91*N91 -> 0
E92: =C92*D92 -> 0 | J92: =H92*I92 -> 0 | O92: =M92*N92 -> 0
E93: =C93*D93 -> 0 | J93: =H93*I93 -> 0 | O93: =M93*N93 -> 0
E94: =C94*D94 -> 0 | J94: =H94*I94 -> 0 | O94: =M94*N94 -> 0
E95: =C95*D95 -> 0 | J95: =H95*I95 -> 0 | O95: =M95*N95 -> 0
E96: =C96*D96 -> 0 | J96: =H96*I96 -> 0 | O96: =M96*N96 -> 0
E97: =C97*D97 -> 0 | J97: =H97*I97 -> 0 | O97: =M97*N97 -> 0
E98: =C98*D98 -> 0 | J98: =H98*I98 -> 0 | O98: =M98*N98 -> 0
E99: =C99*D99 -> 0 | J99: =H99*I99 -> 0 | O99: =M99*N99 -> 0
E100: =C100*D100 -> 0 | J100: =H100*I100 -> 0 | O100: =M100*N100 -> 0
E101: =C101*D101 -> 0 | J101: =H101*I101 -> 0 | O101: =M101*N101 -> 0
... E106: =C106*D106 -> 0 | J106: =H106*I106 -> 0 | O106: =M106*N106 -> 0
E107: =C107*D107 -> 0 | F107: =G107 | J107: =H107*I107 -> 0 | O107: =M107*N107 -> 0
B108: TOTAL EXPENSE | E108: =SUM(E80:E107) -> 0 | F108: [Program] Logistics | G108: TOTAL EXPENSE | J108: =SUM(J83:J107) -> 0 | L108: TOTAL EXPENSE | O108: =SUM(O83:O107) -> 0
B110: ='🏦COVER🏦'!D13 -> #REF! | C110: P | D110: Q | E110: Total | G110: =B110 -> #REF! | H110: P | I110: Q | J110: Total | L110: =B110 -> #REF! | M110: P | N110: Q | O110: Total
E111: =C111*D111 -> 0 | F111: =G111 | J111: =H111*I111 -> 0 | O111: =M111*N111 -> 0
E112: =C112*D112 -> 0 | F112: =G112 | J112: =H112*I112 -> 0 | O112: =M112*N112 -> 0
E113: =C113*D113 -> 0 | F113: =G113 | J113: =H113*I113 -> 0 | O113: =M113*N113 -> 0
E114: =C114*D114 -> 0 | F114: =G114 | J114: =H114*I114 -> 0 | O114: =M114*N114 -> 0
E115: =C115*D115 -> 0 | F115: =G115 | J115: =H115*I115 -> 0 | O115: =M115*N115 -> 0
E116: =C116*D116 -> 0 | F116: =G116 | J116: =H116*I116 -> 0 | O116: =M116*N116 -> 0
E117: =C117*D117 -> 0 | F117: =G117 | J117: =H117*I117 -> 0 | O117: =M117*N117 -> 0
E118: =C118*D118 -> 0 | F118: =G118 | J118: =H118*I118 -> 0 | O118: =M118*N118 -> 0
E119: =C119*D119 -> 0 | F119: =G119 | J119: =H119*I119 -> 0 | O119: =M119*N119 -> 0
E120: =C120*D120 -> 0 | J120: =H120*I120 -> 0 | O120: =M120*N120 -> 0
E121: =C121*D121 -> 0 | J121: =H121*I121 -> 0 | O121: =M121*N121 -> 0
E122: =C122*D122 -> 0 | J122: =H122*I122 -> 0 | O122: =M122*N122 -> 0
E123: =C123*D123 -> 0 | J123: =H123*I123 -> 0 | O123: =M123*N123 -> 0
E124: =C124*D124 -> 0 | J124: =H124*I124 -> 0 | O124: =M124*N124 -> 0
E125: =C125*D125 -> 0 | J125: =H125*I125 -> 0 | O125: =M125*N125 -> 0
E126: =C126*D126 -> 0 | J126: =H126*I126 -> 0 | O126: =M126*N126 -> 0
E127: =C127*D127 -> 0 | J127: =H127*I127 -> 0 | O127: =M127*N127 -> 0
E128: =C128*D128 -> 0 | J128: =H128*I128 -> 0 | O128: =M128*N128 -> 0
...

Sheet 💸BUDGET REALIZED💸
B1: Budget Realized
B3: 💲REVENUE💲 | E3: Total
B4: =B8 -> (revenue stream) | E4: =E18 -> 0
B5: TOTAL REVENUE | E5: =SUM(E4) -> 0
B7: REVENUE BREAKDOWN | G7: % Realization
B8: ='💰BUDGET PLAN💰'!G4 -> (revenue stream) | C8: P | D8: Q | E8: Total | G8: Pessimistic | H8: Realistic | I8: Optimistic | M8: P | N8: R | O8: O
E9: =C9*D9 -> 0 | G9: =IF(M9=0,"",E9/M9) | H9: =IF(N9=0,"",E9/N9) | I9: =IF(O9=0,"",E9/O9) | K9: =IF(G9="","",IF(I9>=1,$I$8,IF(H9>=1,$H$8,$G$8))) | M9: =SUMIF('💰BUDGET PLAN💰'!$B$5:$B$10,B9,'💰BUDGET PLAN💰'!$E$5:$E$10) -> 0 | N9: =SUMIF('💰BUDGET PLAN💰'!$G$5:$G$10,B9,'💰BUDGET PLAN💰'!$J$5:$J$10) -> 0 | O9: =SUMIF('💰BUDGET PLAN💰'!$L$5:$L$10,B9,'💰BUDGET PLAN💰'!$O$5:$O$10) -> 0
E10: =C10*D10 -> 0 | G10: =IF(M10=0,"",E10/M10) | H10: =IF(N10=0,"",E10/N10) | I10: =IF(O10=0,"",E10/O10) | K10: =IF(G10="","",IF(I10>=1,$I$8,IF(H10>=1,$H$8,$G$8))) | M10: =SUMIF('💰BUDGET PLAN💰'!$B$5:$B$10,B10,'💰BUDGET PLAN💰'!$E$5:$E$10) -> 0 | N10: =SUMIF('💰BUDGET PLAN💰'!$G$5:$G$10,B10,'💰BUDGET PLAN💰'!$J$5:$J$10) -> 0 | O10: =SUMIF('💰BUDGET PLAN💰'!$L$5:$L$10,B10,'💰BUDGET PLAN💰'!$O$5:$O$10) -> 0
E11: =C11*D11 -> 0 | G11: =IF(M11=0,"",E11/M11) | H11: =IF(N11=0,"",E11/N11) | I11: =IF(O11=0,"",E11/O11) | K11: =IF(G11="","",IF(I11>=1,$I$8,IF(H11>=1,$H$8,$G$8))) | M11: =SUMIF('💰BUDGET PLAN💰'!$B$5:$B$10,B11,'💰BUDGET PLAN💰'!$E$5:$E$10) -> 0 | N11: =SUMIF('💰BUDGET PLAN💰'!$G$5:$G$10,B11,'💰BUDGET PLAN💰'!$J$5:$J$10) -> 0 | O11: =SUMIF('💰BUDGET PLAN💰'!$L$5:$L$10,B11,'💰BUDGET PLAN💰'!$O$5:$O$10) -> 0
E12: =C12*D12 -> 0 | G12: =IF(M12=0,"",E12/M12) | H12: =IF(N12=0,"",E12/N12) | I12: =IF(O12=0,"",E12/O12) | K12: =IF(G12="","",IF(I12>=1,$I$8,IF(H12>=1,$H$8,$G$8))) | M12: =SUMIF('💰BUDGET PLAN💰'!$B$5:$B$10,B12,'💰BUDGET PLAN💰'!$E$5:$E$10) -> 0 | N12: =SUMIF('💰BUDGET PLAN💰'!$G$5:$G$10,B12,'💰BUDGET PLAN💰'!$J$5:$J$10) -> 0 | O12: =SUMIF('💰BUDGET PLAN💰'!$L$5:$L$10,B12,'💰BUDGET PLAN💰'!$O$5:$O$10) -> 0
E13: =C13*D13 -> 0 | G13: =IF(M13=0,"",E13/M13) | H13: =IF(N13=0,"",E13/N13) | I13: =IF(O13=0,"",E13/O13)
E14: =C14*D14 -> 0 | G14: =IF(M14=0,"",E14/M14) | H14: =IF(N14=0,"",E14/N14) | I14: =IF(O14=0,"",E14/O14)
E15: =C15*D15 -> 0 | G15: =IF(M15=0,"",E15/M15) | H15: =IF(N15=0,"",E15/N15) | I15: =IF(O15=0,"",E15/O15)
E16: =C16*D16 -> 0 | G16: =IF(M16=0,"",E16/M16) | H16: =IF(N16=0,"",E16/N16) | I16: =IF(O16=0,"",E16/O16)
E17: =C17*D17 -> 0 | G17: =IF(M17=0,"",E17/M17) | H17: =IF(N17=0,"",E17/N17) | I17: =IF(O17=0,"",E17/O17)
B18: TOTAL REVENUE | E18: =SUM(E9:E17) -> 0 | G18: =IF(M18=0,"",E18/M18) | H18: =IF(N18=0,"",E18/N18) | I18: =IF(O18=0,"",E18/O18) | K18: =IF(G18="","",IF(I18>=1,$I$8,IF(H18>=1,$H$8,$G$8))) | M18: ='💰BUDGET PLAN💰'!E27 -> 0 | N18: ='💰BUDGET PLAN💰'!J27 -> 0 | O18: ='💰BUDGET PLAN💰'!O27 -> 0
B20: 📉EXPENSE📉 | E20: Total
B21: =B32 -> ACARA | E21: =E47 -> 1000000 | K21: =IF(G21="","",IF(I21>=1,$I$8,IF(H21>=1,$H$8,$G$8))) | M21: ='💰BUDGET PLAN💰'!E30 -> 0 | N21: ='💰BUDGET PLAN💰'!J30 -> 0 | O21: =#REF! -> #REF!
B22: =B49 -> Divisi A | E22: =E78 -> 0 | K22: =IF(G22="","",IF(I22>=1,$I$8,IF(H22>=1,$H$8,$G$8))) | M22: ='💰BUDGET PLAN💰'!E31 -> 0 | N22: ='💰BUDGET PLAN💰'!J31 -> 0 | O22: =#REF! -> #REF!
B23: =B80 -> Divisi A | E23: =E100 -> 0 | K23: =IF(G23="","",IF(I23>=1,$I$8,IF(H23>=1,$H$8,$G$8))) | M23: ='💰BUDGET PLAN💰'!E32 -> 0 | N23: ='💰BUDGET PLAN💰'!J32 -> 0 | O23: =#REF! -> #REF!
B24: =B102 -> Divisi A | E24: =E115 -> 0 | K24: =IF(G24="","",IF(I24>=1,$I$8,IF(H24>=1,$H$8,$G$8))) | M24: ='💰BUDGET PLAN💰'!E33 -> 0 | N24: ='💰BUDGET PLAN💰'!J33 -> 0 | O24: =#REF! -> #REF!
B25: =B117 -> Divisi A | E25: =E127 -> 0 | K25: =IF(G25="","",IF(I25>=1,$I$8,IF(H25>=1,$H$8,$G$8))) | M25: ='💰BUDGET PLAN💰'!E34 -> 0 | N25: ='💰BUDGET PLAN💰'!J34 -> 0 | O25: =#REF! -> #REF!
B26: =B129 -> Divisi A | E26: =E139 -> 0 | K26: =IF(G26="","",IF(I26>=1,$I$8,IF(H26>=1,$H$8,$G$8))) | M26: ='💰BUDGET PLAN💰'!E35 -> 0 | N26: ='💰BUDGET PLAN💰'!J35 -> 0 | O26: =#REF! -> #REF!
B27: TOTAL EXPENSES | E27: =SUM(E21:E26) -> 1000000 | K27: =IF(G27="","",IF(I27>=1,$I$8,IF(H27>=1,$H$8,$G$8))) | M27: =#REF! -> #REF! | N27: =#REF! -> #REF! | O27: =#REF! -> #REF!
B29: 💲NET PROFIT💲 | E29: =E5-E27 -> -1000000 | K29: =IF(G29="","",IF(I29>=1,$I$8,IF(H29>=1,$H$8,$G$8))) | M29: ='💰BUDGET PLAN💰'!E37 -> 0 | N29: ='💰BUDGET PLAN💰'!J37 -> 0 | O29: ='💰BUDGET PLAN💰'!O37 -> 0
B31: EXPENSE BREAKDOWN
B32: ACARA | C32: P | D32: Q | E32: Total | G32: % Realization | M32: P | N32: R | O32: O
B33: banner | C33: 200000 | D33: 5 | E33: =C33*D33 -> 1000000 | G33: =IF(M33=0,"",E33/M33) | H33: =IF(N33=0,"",E33/N33) | I33: =IF(O33=0,"",E33/O33) | K33: =IF(G33="","",IF(I33>=1,$I$8,IF(H33>=1,$H$8,$G$8))) | M33: =SUMIF('💰BUDGET PLAN💰'!$B$41:$B$69,B33,'💰BUDGET PLAN💰'!$E$41:$E$69) -> 0 | N33: =SUMIF('💰BUDGET PLAN💰'!$G$41:$G$69,B33,'💰BUDGET PLAN💰'!$J$41:$J$69) -> 0 | O33: =SUMIF('💰BUDGET PLAN💰'!$L$41:$L$69,'💸BUDGET REALIZED💸'!B33,'💰BUDGET PLAN💰'!$O$41:$O$69) -> 0
E34: =C34*D34 -> 0 | G34: =IF(M34=0,"",E34/M34) | H34: =IF(N34=0,"",E34/N34) | I34: =IF(O34=0,"",E34/O34) | K34: =IF(G34="","",IF(I34>=1,$I$8,IF(H34>=1,$H$8,$G$8))) | M34: =SUMIF('💰BUDGET PLAN💰'!$B$41:$B$69,B34,'💰BUDGET PLAN💰'!$E$41:$E$69) -> 0 | N34: =SUMIF('💰BUDGET PLAN💰'!$G$41:$G$69,B34,'💰BUDGET PLAN💰'!$J$41:$J$69) -> 0 | O34: =SUMIF('💰BUDGET PLAN💰'!$L$41:$L$69,'💸BUDGET REALIZED💸'!B34,'💰BUDGET PLAN💰'!$O$41:$O$69) -> 0
E35: =C35*D35 -> 0 | G35: =IF(M35=0,"",E35/M35) | H35: =IF(N35=0,"",E35/N35) | I35: =IF(O35=0,"",E35/O35) | K35: =IF(G35="","",IF(I35>=1,$I$8,IF(H35>=1,$H$8,$G$8))) | M35: =SUMIF('💰BUDGET PLAN💰'!$B$41:$B$69,B35,'💰BUDGET PLAN💰'!$E$41:$E$69) -> 0 | N35: =SUMIF('💰BUDGET PLAN💰'!$G$41:$G$69,B35,'💰BUDGET PLAN💰'!$J$41:$J$69) -> 0 | O35: =SUMIF('💰BUDGET PLAN💰'!$L$41:$L$69,'💸BUDGET REALIZED💸'!B35,'💰BUDGET PLAN💰'!$O$41:$O$69) -> 0
E36: =C36*D36 -> 0 | G36: =IF(M36=0,"",E36/M36) | H36: =IF(N36=0,"",E36/N36) | I36: =IF(O36=0,"",E36/O36) | K36: =IF(G36="","",IF(I36>=1,$I$8,IF(H36>=1,$H$8,$G$8))) | M36: =SUMIF('💰BUDGET PLAN💰'!$B$41:$B$69,B36,'💰BUDGET PLAN💰'!$E$41:$E$69) -> 0 | N36: =SUMIF('💰BUDGET PLAN💰'!$G$41:$G$69,B36,'💰BUDGET PLAN💰'!$J$41:$J$69) -> 0 | O36: =SUMIF('💰BUDGET PLAN💰'!$L$41:$L$69,'💸BUDGET REALIZED💸'!B36,'💰BUDGET PLAN💰'!$O$41:$O$69) -> 0
E37: =C37*D37 -> 0 | G37: =IF(M37=0,"",E37/M37) | H37: =IF(N37=0,"",E37/N37) | I37: =IF(O37=0,"",E37/O37) | K37: =IF(G37="","",IF(I37>=1,$I$8,IF(H37>=1,$H$8,$G$8))) | M37: =SUMIF('💰BUDGET PLAN💰'!$B$41:$B$69,B37,'💰BUDGET PLAN💰'!$E$41:$E$69) -> 0 | N37: =SUMIF('💰BUDGET PLAN💰'!$G$41:$G$69,B37,'💰BUDGET PLAN💰'!$J$41:$J$69) -> 0 | O37: =SUMIF('💰BUDGET PLAN💰'!$L$41:$L$69,'💸BUDGET REALIZED💸'!B37,'💰BUDGET PLAN💰'!$O$41:$O$69) -> 0
E38: =C38*D38 -> 0 | G38: =IF(M38=0,"",E38/M38) | H38: =IF(N38=0,"",E38/N38) | I38: =IF(O38=0,"",E38/O38) | K38: =IF(G38="","",IF(I38>=1,$I$8,IF(H38>=1,$H$8,$G$8))) | M38: =SUMIF('💰BUDGET PLAN💰'!$B$41:$B$69,B38,'💰BUDGET PLAN💰'!$E$41:$E$69) -> 0 | N38: =SUMIF('💰BUDGET PLAN💰'!$G$41:$G$69,B38,'💰BUDGET PLAN💰'!$J$41:$J$69) -> 0 | O38: =SUMIF('💰BUDGET PLAN💰'!$L$41:$L$69,'💸BUDGET REALIZED💸'!B38,'💰BUDGET PLAN💰'!$O$41:$O$69) -> 0
E39: =C39*D39 -> 0 | G39: =IF(M39=0,"",E39/M39) | H39: =IF(N39=0,"",E39/N39) | I39: =IF(O39=0,"",E39/O39) | K39: =IF(G39="","",IF(I39>=1,$I$8,IF(H39>=1,$H$8,$G$8))) | M39: =SUMIF('💰BUDGET PLAN💰'!$B$41:$B$69,B39,'💰BUDGET PLAN💰'!$E$41:$E$69) -> 0 | N39: =SUMIF('💰BUDGET PLAN💰'!$G$41:$G$69,B39,'💰BUDGET PLAN💰'!$J$41:$J$69) -> 0 | O39: =SUMIF('💰BUDGET PLAN💰'!$L$41:$L$69,'💸BUDGET REALIZED💸'!B39,'💰BUDGET PLAN💰'!$O$41:$O$69) -> 0
E40: =C40*D40 -> 0 | G40: =IF(M40=0,"",E40/M40) | H40: =IF(N40=0,"",E40/N40) | I40: =IF(O40=0,"",E40/O40) | K40: =IF(G40="","",IF(I40>=1,$I$8,IF(H40>=1,$H$8,$G$8))) | M40: =SUMIF('💰BUDGET PLAN💰'!$B$41:$B$69,B40,'💰BUDGET PLAN💰'!$E$41:$E$69) -> 0 | N40: =SUMIF('💰BUDGET PLAN💰'!$G$41:$G$69,B40,'💰BUDGET PLAN💰'!$J$41:$J$69) -> 0 | O40: =SUMIF('💰BUDGET PLAN💰'!$L$41:$L$69,'💸BUDGET REALIZED💸'!B40,'💰BUDGET PLAN💰'!$O$41:$O$69) -> 0
E41: =C41*D41 -> 0 | G41: =IF(M41=0,"",E41/M41) | H41: =IF(N41=0,"",E41/N41) | I41: =IF(O41=0,"",E41/O41) | K41: =IF(G41="","",IF(I41>=1,$I$8,IF(H41>=1,$H$8,$G$8))) | M41: =SUMIF('💰BUDGET PLAN💰'!$B$41:$B$69,B41,'💰BUDGET PLAN💰'!$E$41:$E$69) -> 0 | N41: =SUMIF('💰BUDGET PLAN💰'!$G$41:$G$69,B41,'💰BUDGET PLAN💰'!$J$41:$J$69) -> 0 | O41: =SUMIF('💰BUDGET PLAN💰'!$L$41:$L$69,'💸BUDGET REALIZED💸'!B41,'💰BUDGET PLAN💰'!$O$41:$O$69) -> 0
E42: =C42*D42 -> 0 | G42: =IF(M42=0,"",E42/M42) | H42: =IF(N42=0,"",E42/N42) | I42: =IF(O42=0,"",E42/O42) | K42: =IF(G42="","",IF(I42>=1,$I$8,IF(H42>=1,$H$8,$G$8))) | M42: =SUMIF('💰BUDGET PLAN💰'!$B$41:$B$69,B42,'💰BUDGET PLAN💰'!$E$41:$E$69) -> 0 | N42: =SUMIF('💰BUDGET PLAN💰'!$G$41:$G$69,B42,'💰BUDGET PLAN💰'!$J$41:$J$69) -> 0 | O42: =SUMIF('💰BUDGET PLAN💰'!$L$41:$L$69,'💸BUDGET REALIZED💸'!B42,'💰BUDGET PLAN💰'!$O$41:$O$69) -> 0
E43: =C43*D43 -> 0 | G43: =IF(M43=0,"",E43/M43) | H43: =IF(N43=0,"",E43/N43) | I43: =IF(O43=0,"",E43/O43)
E44: =C44*D44 -> 0 | G44: =IF(M44=0,"",E44/M44) | H44: =IF(N44=0,"",E44/N44) | I44: =IF(O44=0,"",E44/O44)
E45: =C45*D45 -> 0 | G45: =IF(M45=0,"",E45/M45) | H45: =IF(N45=0,"",E45/N45) | I45: =IF(O45=0,"",E45/O45)
E46: =C46*D46 -> 0 | G46: =IF(M46=0,"",E46/M46) | H46: =IF(N46=0,"",E46/N46) | I46: =IF(O46=0,"",E46/O46) | K46: =IF(G46="","",IF(I46>=1,$I$8,IF(H46>=1,$H$8,$G$8))) | M46: =SUMIF('💰BUDGET PLAN💰'!$B$41:$B$69,B46,'💰BUDGET PLAN💰'!$E$41:$E$69) -> 0 | N46: =SUMIF('💰BUDGET PLAN💰'!$G$41:$G$69,B46,'💰BUDGET PLAN💰'!$J$41:$J$69) -> 0 | O46: =SUMIF('💰BUDGET PLAN💰'!$L$41:$L$69,'💸BUDGET REALIZED💸'!B46,'💰BUDGET PLAN💰'!$O$41:$O$69) -> 0
B47: TOTAL | E47: =SUM(E33:E46) -> 1000000 | G47: =IF(M47=0,"",E47/M47) | H47: =IF(N47=0,"",E47/N47) | I47: =IF(O47=0,"",E47/O47) | K47: =IF(G47="","",IF(I47>=1,$I$8,IF(H47>=1,$H$8,$G$8))) | M47: ='💰BUDGET PLAN💰'!E77 -> 0 | N47: ='💰BUDGET PLAN💰'!J77 -> 0 | O47: ='💰BUDGET PLAN💰'!O77 -> 0
B49: Divisi A | C49: P | D49: Q | E49: Total | G49: % Realization
E50: =C50*D50 -> 0 | G50: =IF(M50=0,"",E50/M50) | H50: =IF(N50=0,"",E50/N50) | I50: =IF(O50=0,"",E50/O50) | K50: =IF(G50="","",IF(I50>=1,$I$8,IF(H50>=1,$H$8,$G$8))) | M50: =SUMIF('💰BUDGET PLAN💰'!$B$80:$B$107,B50,'💰BUDGET PLAN💰'!$E$80:$E$107) -> 0 | N50: =SUMIF('💰BUDGET PLAN💰'!$G$80:$G$107,'💸BUDGET REALIZED💸'!B50,'💰BUDGET PLAN💰'!$J$80:$J$107) -> 0 | O50: =SUMIF('💰BUDGET PLAN💰'!$L$80:$L$107,'💸BUDGET REALIZED💸'!B50,'💰BUDGET PLAN💰'!$O$80:$O$107) -> 0
E51: =C50*D51 -> 0 | G51: =IF(M51=0,"",E51/M51) | H51: =IF(N51=0,"",E51/N51) | I51: =IF(O51=0,"",E51/O51) | K51: =IF(G51="","",IF(I51>=1,$I$8,IF(H51>=1,$H$8,$G$8))) | M51: =SUMIF('💰BUDGET PLAN💰'!$B$80:$B$107,B51,'💰BUDGET PLAN💰'!$E$80:$E$107) -> 0 | N51: =SUMIF('💰BUDGET PLAN💰'!$G$80:$G$107,'💸BUDGET REALIZED💸'!B51,'💰BUDGET PLAN💰'!$J$80:$J$107) -> 0 | O51: =SUMIF('💰BUDGET PLAN💰'!$L$80:$L$107,'💸BUDGET REALIZED💸'!B51,'💰BUDGET PLAN💰'!$O$80:$O$107) -> 0
E52: =C52*D52 -> 0 | G52: =IF(M52=0,"",E52/M52) | H52: =IF(N52=0,"",E52/N52) | I52: =IF(O52=0,"",E52/O52) | K52: =IF(G52="","",IF(I52>=1,$I$8,IF(H52>=1,$H$8,$G$8))) | M52: =SUMIF('💰BUDGET PLAN💰'!$B$80:$B$107,B52,'💰BUDGET PLAN💰'!$E$80:$E$107) -> 0 | N52: =SUMIF('💰BUDGET PLAN💰'!$G$80:$G$107,'💸BUDGET REALIZED💸'!B52,'💰BUDGET PLAN💰'!$J$80:$J$107) -> 0 | O52: =SUMIF('💰BUDGET PLAN💰'!$L$80:$L$107,'💸BUDGET REALIZED💸'!B52,'💰BUDGET PLAN💰'!$O$80:$O$107) -> 0
E53: =C53*D53 -> 0 | G53: =IF(M53=0,"",E53/M53) | H53: =IF(N53=0,"",E53/N53) | I53: =IF(O53=0,"",E53/O53) | K53: =IF(G53="","",IF(I53>=1,$I$8,IF(H53>=1,$H$8,$G$8))) | M53: =SUMIF('💰BUDGET PLAN💰'!$B$80:$B$107,B53,'💰BUDGET PLAN💰'!$E$80:$E$107) -> 0 | N53: =SUMIF('💰BUDGET PLAN💰'!$G$80:$G$107,'💸BUDGET REALIZED💸'!B53,'💰BUDGET PLAN💰'!$J$80:$J$107) -> 0 | O53: =SUMIF('💰BUDGET PLAN💰'!$L$80:$L$107,'💸BUDGET REALIZED💸'!B53,'💰BUDGET PLAN💰'!$O$80:$O$107) -> 0
E54: =C54*D54 -> 0 | G54: =IF(M54=0,"",E54/M54) | H54: =IF(N54=0,"",E54/N54) | I54: =IF(O54=0,"",E54/O54) | M54: =SUMIF('💰BUDGET PLAN💰'!$B$80:$B$107,B54,'💰BUDGET PLAN💰'!$E$80:$E$107) -> 0 | N54: =SUMIF('💰BUDGET PLAN💰'!$G$80:$G$107,'💸BUDGET REALIZED💸'!B54,'💰BUDGET PLAN💰'!$J$80:$J$107) -> 0 | O54: =SUMIF('💰BUDGET PLAN💰'!$L$80:$L$107,'💸BUDGET REALIZED💸'!B54,'💰BUDGET PLAN💰'!$O$80:$O$107) -> 0
E55: =C55*D55 -> 0 | G55: =IF(M55=0,"",E55/M55) | H55: =IF(N55=0,"",E55/N55) | I55: =IF(O55=0,"",E55/O55) | M55: =SUMIF('💰BUDGET PLAN💰'!$B$80:$B$107,B55,'💰BUDGET PLAN💰'!$E$80:$E$107) -> 0 | N55: =SUMIF('💰BUDGET PLAN💰'!$G$80:$G$107,'💸BUDGET REALIZED💸'!B55,'💰BUDGET PLAN💰'!$J$80:$J$107) -> 0 | O55: =SUMIF('💰BUDGET PLAN💰'!$L$80:$L$107,'💸BUDGET REALIZED💸'!B55,'💰BUDGET PLAN💰'!$O$80:$O$107) -> 0
E56: =C56*D56 -> 0 | G56: =IF(M56=0,"",E56/M56) | H56: =IF(N56=0,"",E56/N56) | I56: =IF(O56=0,"",E56/O56) | M56: =SUMIF('💰BUDGET PLAN💰'!$B$80:$B$107,B56,'💰BUDGET PLAN💰'!$E$80:$E$107) -> 0 | N56: =SUMIF('💰BUDGET PLAN💰'!$G$80:$G$107,'💸BUDGET REALIZED💸'!B56,'💰BUDGET PLAN💰'!$J$80:$J$107) -> 0 | O56: =SUMIF('💰BUDGET PLAN💰'!$L$80:$L$107,'💸BUDGET REALIZED💸'!B56,'💰BUDGET PLAN💰'!$O$80:$O$107) -> 0
E57: =C57*D57 -> 0 | G57: =IF(M57=0,"",E57/M57) | H57: =IF(N57=0,"",E57/N57) | I57: =IF(O57=0,"",E57/O57) | M57: =SUMIF('💰BUDGET PLAN💰'!$B$80:$B$107,B57,'💰BUDGET PLAN💰'!$E$80:$E$107) -> 0 | N57: =SUMIF('💰BUDGET PLAN💰'!$G$80:$G$107,'💸BUDGET REALIZED💸'!B57,'💰BUDGET PLAN💰'!$J$80:$J$107) -> 0 | O57: =SUMIF('💰BUDGET PLAN💰'!$L$80:$L$107,'💸BUDGET REALIZED💸'!B57,'💰BUDGET PLAN💰'!$O$80:$O$107) -> 0
E58: =C58*D58 -> 0 | G58: =IF(M58=0,"",E58/M58) | H58: =IF(N58=0,"",E58/N58) | I58: =IF(O58=0,"",E58/O58) | M58: =SUMIF('💰BUDGET PLAN💰'!$B$80:$B$107,B58,'💰BUDGET PLAN💰'!$E$80:$E$107) -> 0 | N58: =SUMIF('💰BUDGET PLAN💰'!$G$80:$G$107,'💸BUDGET REALIZED💸'!B58,'💰BUDGET PLAN💰'!$J$80:$J$107) -> 0 | O58: =SUMIF('💰BUDGET PLAN💰'!$L$80:$L$107,'💸BUDGET REALIZED💸'!B58,'💰BUDGET PLAN💰'!$O$80:$O$107) -> 0
E59: =C59*D59 -> 0 | G59: =IF(M59=0,"",E59/M59) | H59: =IF(N59=0,"",E59/N59) | I59: =IF(O59=0,"",E59/O59) | M59: =SUMIF('💰BUDGET PLAN💰'!$B$80:$B$107,B59,'💰BUDGET PLAN💰'!$E$80:$E$107) -> 0 | N59: =SUMIF('💰BUDGET PLAN💰'!$G$80:$G$107,'💸BUDGET REALIZED💸'!B59,'💰BUDGET PLAN💰'!$J$80:$J$107) -> 0 | O59: =SUMIF('💰BUDGET PLAN💰'!$L$80:$L$107,'💸BUDGET REALIZED💸'!B59,'💰BUDGET PLAN💰'!$O$80:$O$107) -> 0
E60: =C60*D60 -> 0 | G60: =IF(M60=0,"",E60/M60) | H60: =IF(N60=0,"",E60/N60) | I60: =IF(O60=0,"",E60/O60) | M60: =SUMIF('💰BUDGET PLAN💰'!$B$80:$B$107,B60,'💰BUDGET PLAN💰'!$E$80:$E$107) -> 0 | N60: =SUMIF('💰BUDGET PLAN💰'!$G$80:$G$107,'💸BUDGET REALIZED💸'!B60,'💰BUDGET PLAN💰'!$J$80:$J$107) -> 0 | O60: =SUMIF('💰BUDGET PLAN💰'!$L$80:$L$107,'💸BUDGET REALIZED💸'!B60,'💰BUDGET PLAN💰'!$O$80:$O$107) -> 0
E61: =C61*D61 -> 0 | G61: =IF(M61=0,"",E61/M61) | H61: =IF(N61=0,"",E61/N61) | I61: =IF(O61=0,"",E61/O61) | K61: =IF(G61="","",IF(I61>=1,$I$8,IF(H61>=1,$H$8,$G$8))) | M61: =SUMIF('💰BUDGET PLAN💰'!$B$80:$B$107,B61,'💰BUDGET PLAN💰'!$E$80:$E$107) -> 0 | N61: =SUMIF('💰BUDGET PLAN💰'!$G$80:$G$107,'💸BUDGET REALIZED💸'!B61,'💰BUDGET PLAN💰'!$J$80:$J$107) -> 0 | O61: =SUMIF('💰BUDGET PLAN💰'!$L$80:$L$107,'💸BUDGET REALIZED💸'!B61,'💰BUDGET PLAN💰'!$O$80:$O$107) -> 0
E62: =C62*D62 -> 0 | G62: =IF(M62=0,"",E62/M62) | H62: =IF(N62=0,"",E62/N62) | I62: =IF(O62=0,"",E62/O62) | K62: =IF(G62="","",IF(I62>=1,$I$8,IF(H62>=1,$H$8,$G$8))) | M62: =SUMIF('💰BUDGET PLAN💰'!$B$80:$B$107,B62,'💰BUDGET PLAN💰'!$E$80:$E$107) -> 0 | N62: =SUMIF('💰BUDGET PLAN💰'!$G$80:$G$107,'💸BUDGET REALIZED💸'!B62,'💰BUDGET PLAN💰'!$J$80:$J$107) -> 0 | O62: =SUMIF('💰BUDGET PLAN💰'!$L$80:$L$107,'💸BUDGET REALIZED💸'!B62,'💰BUDGET PLAN💰'!$O$80:$O$107) -> 0
E63: =C63*D63 -> 0 | G63: =IF(M63=0,"",E63/M63) | H63: =IF(N63=0,"",E63/N63) | I63: =IF(O63=0,"",E63/O63) | K63: =IF(G63="","",IF(I63>=1,$I$8,IF(H63>=1,$H$8,$G$8))) | M63: =SUMIF('💰BUDGET PLAN💰'!$B$80:$B$107,B63,'💰BUDGET PLAN💰'!$E$80:$E$107) -> 0 | N63: =SUMIF('💰BUDGET PLAN💰'!$G$80:$G$107,'💸BUDGET REALIZED💸'!B63,'💰BUDGET PLAN💰'!$J$80:$J$107) -> 0 | O63: =SUMIF('💰BUDGET PLAN💰'!$L$80:$L$107,'💸BUDGET REALIZED💸'!B63,'💰BUDGET PLAN💰'!$O$80:$O$107) -> 0
E64: =C64*D64 -> 0 | G64: =IF(M64=0,"",E64/M64) | H64: =IF(N64=0,"",E64/N64) | I64: =IF(O64=0,"",E64/O64) | K64: =IF(G64="","",IF(I64>=1,$I$8,IF(H64>=1,$H$8,$G$8))) | M64: =SUMIF('💰BUDGET PLAN💰'!$B$80:$B$107,B64,'💰BUDGET PLAN💰'!$E$80:$E$107) -> 0 | N64: =SUMIF('💰BUDGET PLAN💰'!$G$80:$G$107,'💸BUDGET REALIZED💸'!B64,'💰BUDGET PLAN💰'!$J$80:$J$107) -> 0 | O64: =SUMIF('💰BUDGET PLAN💰'!$L$80:$L$107,'💸BUDGET REALIZED💸'!B64,'💰BUDGET PLAN💰'!$O$80:$O$107) -> 0
E65: =C65*D65 -> 0 | G65: =IF(M65=0,"",E65/M65) | H65: =IF(N65=0,"",E65/N65) | I65: =IF(O65=0,"",E65/O65) | K65: =IF(G65="","",IF(I65>=1,$I$8,IF(H65>=1,$H$8,$G$8))) | M65: =SUMIF('💰BUDGET PLAN💰'!$B$80:$B$107,B65,'💰BUDGET PLAN💰'!$E$80:$E$107) -> 0 | N65: =SUMIF('💰BUDGET PLAN💰'!$G$80:$G$107,'💸BUDGET REALIZED💸'!B65,'💰BUDGET PLAN💰'!$J$80:$J$107) -> 0 | O65: =SUMIF('💰BUDGET PLAN💰'!$L$80:$L$107,'💸BUDGET REALIZED💸'!B65,'💰BUDGET PLAN💰'!$O$80:$O$107) -> 0
E66: =C66*D66 -> 0 | G66: =IF(M66=0,"",E66/M66) | H66: =IF(N66=0,"",E66/N66) | I66: =IF(O66=0,"",E66/O66) | K66: =IF(G66="","",IF(I66>=1,$I$8,IF(H66>=1,$H$8,$G$8))) | M66: =SUMIF('💰BUDGET PLAN💰'!$B$80:$B$107,B66,'💰BUDGET PLAN💰'!$E$80:$E$107) -> 0 | N66: =SUMIF('💰BUDGET PLAN💰'!$G$80:$G$107,'💸BUDGET REALIZED💸'!B66,'💰BUDGET PLAN💰'!$J$80:$J$107) -> 0 | O66: =SUMIF('💰BUDGET PLAN💰'!$L$80:$L$107,'💸BUDGET REALIZED💸'!B66,'💰BUDGET PLAN💰'!$O$80:$O$107) -> 0
E67: =C67*D67 -> 0 | G67: =IF(M67=0,"",E67/M67) | H67: =IF(N67=0,"",E67/N67) | I67: =IF(O67=0,"",E67/O67)
E68: =C68*D68 -> 0 | G68: =IF(M68=0,"",E68/M68) | H68: =IF(N68=0,"",E68/N68) | I68: =IF(O68=0,"",E68/O68)
E69: =C69*D69 -> 0 | G69: =IF(M69=0,"",E69/M69) | H69: =IF(N69=0,"",E69/N69) | I69: =IF(O69=0,"",E69/O69)
E70: =C70*D70 -> 0 | G70: =IF(M70=0,"",E70/M70) | H70: =IF(N70=0,"",E70/N70) | I70: =IF(O70=0,"",E70/O70)
E71: =C71*D71 -> 0 | G71: =IF(M71=0,"",E71/M71) | H71: =IF(N71=0,"",E71/N71) | I71: =IF(O71=0,"",E71/O71)
E72: =C72*D72 -> 0 | G72: =IF(M72=0,"",E72/M72) | H72: =IF(N72=0,"",E72/N72) | I72: =IF(O72=0,"",E72/O72)
E73: =C73*D73 -> 0 | G73: =IF(M73=0,"",E73/M73) | H73: =IF(N73=0,"",E73/N73) | I73: =IF(O73=0,"",E73/O73)
E74: =C74*D74 -> 0 | G74: =IF(M74=0,"",E74/M74) | H74: =IF(N74=0,"",E74/N74) | I74: =IF(O74=0,"",E74/O74)
E75: =C75*D75 -> 0 | G75: =IF(M75=0,"",E75/M75) | H75: =IF(N75=0,"",E75/N75) | I75: =IF(O75=0,"",E75/O75)
E76: =C76*D76 -> 0 | G76: =IF(M76=0,"",E76/M76) | H76: =IF(N76=0,"",E76/N76) | I76: =IF(O76=0,"",E76/O76)
E77: =C77*D77 -> 0 | G77: =IF(M77=0,"",E77/M77) | H77: =IF(N77=0,"",E77/N77) | I77: =IF(O77=0,"",E77/O77)
B78: TOTAL | E78: =SUM(E50:E77) -> 0 | G78: =IF(M78=0,"",E78/M78) | H78: =IF(N78=0,"",E78/N78) | I78: =IF(O78=0,"",E78/O78) | K78: =IF(G78="","",IF(I78>=1,$I$8,IF(H78>=1,$H$8,$G$8))) | M78: ='💰BUDGET PLAN💰'!E108 -> 0 | N78: ='💰BUDGET PLAN💰'!J108 -> 0 | O78: ='💰BUDGET PLAN💰'!O108 -> 0
B80: Divisi A | C80: P | D80: Q | E80: Total | G80: % Realization
E81: =C81*D81 -> 0 | G81: =IF(M81=0,"",E81/M81) | H81: =IF(N81=0,"",E81/N81) | I81: =IF(O81=0,"",E81/O81) | K81: =IF(G81="","",IF(I81>=1,$I$8,IF(H81>=1,$H$8,$G$8))) | M81: =SUMIF('💰BUDGET PLAN💰'!$B$111:$B$129,'💸BUDGET REALIZED💸'!B81,'💰BUDGET PLAN💰'!$E$111:$E$129) -> 0 | N81: =SUMIF('💰BUDGET PLAN💰'!$G$111:$G$129,'💸BUDGET REALIZED💸'!B81,'💰BUDGET PLAN💰'!$J$111:$J$129) -> 0 | O81: =SUMIF('💰BUDGET PLAN💰'!$L$111:$L$129,'💸BUDGET REALIZED💸'!B81,'💰BUDGET PLAN💰'!$O$111:$O$129) -> 0
E82: =C82*D82 -> 0 | G82: =IF(M82=0,"",E82/M82) | H82: =IF(N82=0,"",E82/N82) | I82: =IF(O82=0,"",E82/O82) | K82: =IF(G82="","",IF(I82>=1,$I$8,IF(H82>=1,$H$8,$G$8))) | M82: =SUMIF('💰BUDGET PLAN💰'!$B$111:$B$129,'💸BUDGET REALIZED💸'!B82,'💰BUDGET PLAN💰'!$E$111:$E$129) -> 0 | N82: =SUMIF('💰BUDGET PLAN💰'!$G$111:$G$129,'💸BUDGET REALIZED💸'!B82,'💰BUDGET PLAN💰'!$J$111:$J$129) -> 0 | O82: =SUMIF('💰BUDGET PLAN💰'!$L$111:$L$129,'💸BUDGET REALIZED💸'!B82,'💰BUDGET PLAN💰'!$O$111:$O$129) -> 0
E83: =C83*D83 -> 0 | G83: =IF(M83=0,"",E83/M83) | H83: =IF(N83=0,"",E83/N83) | I83: =IF(O83=0,"",E83/O83) | K83: =IF(G83="","",IF(I83>=1,$I$8,IF(H83>=1,$H$8,$G$8))) | M83: =SUMIF('💰BUDGET PLAN💰'!$B$111:$B$129,'💸BUDGET REALIZED💸'!B83,'💰BUDGET PLAN💰'!$E$111:$E$129) -> 0 | N83: =SUMIF('💰BUDGET PLAN💰'!$G$111:$G$129,'💸BUDGET REALIZED💸'!B83,'💰BUDGET PLAN💰'!$J$111:$J$129) -> 0 | O83: =SUMIF('💰BUDGET PLAN💰'!$L$111:$L$129,'💸BUDGET REALIZED💸'!B83,'💰BUDGET PLAN💰'!$O$111:$O$129) -> 0
E84: =C84*D84 -> 0 | G84: =IF(M84=0,"",E84/M84) | H84: =IF(N84=0,"",E84/N84) | I84: =IF(O84=0,"",E84/O84) | K84: =IF(G84="","",IF(I84>=1,$I$8,IF(H84>=1,$H$8,$G$8))) | M84: =SUMIF('💰BUDGET PLAN💰'!$B$111:$B$129,'💸BUDGET REALIZED💸'!B84,'💰BUDGET PLAN💰'!$E$111:$E$129) -> 0 | N84: =SUMIF('💰BUDGET PLAN💰'!$G$111:$G$129,'💸BUDGET REALIZED💸'!B84,'💰BUDGET PLAN💰'!$J$111:$J$129) -> 0 | O84: =SUMIF('💰BUDGET PLAN💰'!$L$111:$L$129,'💸BUDGET REALIZED💸'!B84,'💰BUDGET PLAN💰'!$O$111:$O$129) -> 0
E85: =C85*D85 -> 0 | G85: =IF(M85=0,"",E85/M85) | H85: =IF(N85=0,"",E85/N85) | I85: =IF(O85=0,"",E85/O85) | K85: =IF(G85="","",IF(I85>=1,$I$8,IF(H85>=1,$H$8,$G$8))) | M85: =SUMIF('💰BUDGET PLAN💰'!$B$111:$B$129,'💸BUDGET REALIZED💸'!B85,'💰BUDGET PLAN💰'!$E$111:$E$129) -> 0 | N85: =SUMIF('💰BUDGET PLAN💰'!$G$111:$G$129,'💸BUDGET REALIZED💸'!B85,'💰BUDGET PLAN💰'!$J$111:$J$129) -> 0 | O85: =SUMIF('💰BUDGET PLAN💰'!$L$111:$L$129,'💸BUDGET REALIZED💸'!B85,'💰BUDGET PLAN💰'!$O$111:$O$129) -> 0
E86: 0 | G86: =IF(M86=0,"",E86/M86) | H86: =IF(N86=0,"",E86/N86) | I86: =IF(O86=0,"",E86/O86) | K86: =IF(G86="","",IF(I86>=1,$I$8,IF(H86>=1,$H$8,$G$8))) | M86: =SUMIF('💰BUDGET PLAN💰'!$B$111:$B$129,'💸BUDGET REALIZED💸'!B86,'💰BUDGET PLAN💰'!$E$111:$E$129) -> 0 | N86: =SUMIF('💰BUDGET PLAN💰'!$G$111:$G$129,'💸BUDGET REALIZED💸'!B86,'💰BUDGET PLAN💰'!$J$111:$J$129) -> 0 | O86: =SUMIF('💰BUDGET PLAN💰'!$L$111:$L$129,'💸BUDGET REALIZED💸'!B86,'💰BUDGET PLAN💰'!$O$111:$O$129) -> 0
E87: 0 | G87: =IF(M87=0,"",E87/M87) | H87: =IF(N87=0,"",E87/N87) | I87: =IF(O87=0,"",E87/O87) | K87: =IF(G87="","",IF(I87>=1,$I$8,IF(H87>=1,$H$8,$G$8))) | M87: =SUMIF('💰BUDGET PLAN💰'!$B$111:$B$129,'💸BUDGET REALIZED💸'!B87,'💰BUDGET PLAN💰'!$E$111:$E$129) -> 0 | N87: =SUMIF('💰BUDGET PLAN💰'!$G$111:$G$129,'💸BUDGET REALIZED💸'!B87,'💰BUDGET PLAN💰'!$J$111:$J$129) -> 0 | O87: =SUMIF('💰BUDGET PLAN💰'!$L$111:$L$129,'💸BUDGET REALIZED💸'!B87,'💰BUDGET PLAN💰'!$O$111:$O$129) -> 0
E88: 0 | G88: =IF(M88=0,"",E88/M88) | H88: =IF(N88=0,"",E88/N88) | I88: =IF(O88=0,"",E88/O88) | K88: =IF(G88="","",IF(I88>=1,$I$8,IF(H88>=1,$H$8,$G$8))) | M88: =SUMIF('💰BUDGET PLAN💰'!$B$111:$B$129,'💸BUDGET REALIZED💸'!B88,'💰BUDGET PLAN💰'!$E$111:$E$129) -> 0 | N88: =SUMIF('💰BUDGET PLAN💰'!$G$111:$G$129,'💸BUDGET REALIZED💸'!B88,'💰BUDGET PLAN💰'!$J$111:$J$129) -> 0 | O88: =SUMIF('💰BUDGET PLAN💰'!$L$111:$L$129,'💸BUDGET REALIZED💸'!B88,'💰BUDGET PLAN💰'!$O$111:$O$129) -> 0
E89: =C89*D89 -> 0 | G89: =IF(M89=0,"",E89/M89) | H89: =IF(N89=0,"",E89/N89) | I89: =IF(O89=0,"",E89/O89) | K89: =IF(G89="","",IF(I89>=1,$I$8,IF(H89>=1,$H$8,$G$8))) | M89: =SUMIF('💰BUDGET PLAN💰'!$B$111:$B$129,'💸BUDGET REALIZED💸'!B89,'💰BUDGET PLAN💰'!$E$111:$E$129) -> 0 | N89: =SUMIF('💰BUDGET PLAN💰'!$G$111:$G$129,'💸BUDGET REALIZED💸'!B89,'💰BUDGET PLAN💰'!$J$111:$J$129) -> 0 | O89: =SUMIF('💰BUDGET PLAN💰'!$L$111:$L$129,'💸BUDGET REALIZED💸'!B89,'💰BUDGET PLAN💰'!$O$111:$O$129) -> 0
E90: =C90*D90 -> 0 | G90: =IF(M90=0,"",E90/M90) | H90: =IF(N90=0,"",E90/N90) | I90: =IF(O90=0,"",E90/O90) | K90: =IF(G90="","",IF(I90>=1,$I$8,IF(H90>=1,$H$8,$G$8))) | M90: =SUMIF('💰BUDGET PLAN💰'!$B$111:$B$129,'💸BUDGET REALIZED💸'!B90,'💰BUDGET PLAN💰'!$E$111:$E$129) -> 0 | N90: =SUMIF('💰BUDGET PLAN💰'!$G$111:$G$129,'💸BUDGET REALIZED💸'!B90,'💰BUDGET PLAN💰'!$J$111:$J$129) -> 0 | O90: =SUMIF('💰BUDGET PLAN💰'!$L$111:$L$129,'💸BUDGET REALIZED💸'!B90,'💰BUDGET PLAN💰'!$O$111:$O$129) -> 0
E91: =C91*D91 -> 0 | G91: =IF(M91=0,"",E91/M91) | H91: =IF(N91=0,"",E91/N91) | I91: =IF(O91=0,"",E91/O91) | K91: =IF(G91="","",IF(I91>=1,$I$8,IF(H91>=1,$H$8,$G$8))) | M91: =SUMIF('💰BUDGET PLAN💰'!$B$111:$B$129,'💸BUDGET REALIZED💸'!B91,'💰BUDGET PLAN💰'!$E$111:$E$129) -> 0 | N91: =SUMIF('💰BUDGET PLAN💰'!$G$111:$G$129,'💸BUDGET REALIZED💸'!B91,'💰BUDGET PLAN💰'!$J$111:$J$129) -> 0 | O91: =SUMIF('💰BUDGET PLAN💰'!$L$111:$L$129,'💸BUDGET REALIZED💸'!B91,'💰BUDGET PLAN💰'!$O$111:$O$129) -> 0
E92: =C92*D92 -> 0 | G92: =IF(M92=0,"",E92/M92) | H92: =IF(N92=0,"",E92/N92) | I92: =IF(O92=0,"",E92/O92)
E93: =C93*D93 -> 0 | G93: =IF(M93=0,"",E93/M93) | H93: =IF(N93=0,"",E93/N93) | I93: =IF(O93=0,"",E93/O93)
E94: =C94*D94 -> 0 | G94: =IF(M94=0,"",E94/M94) | H94: =IF(N94=0,"",E94/N94) | I94: =IF(O94=0,"",E94/O94)
E95: =C95*D95 -> 0 | G95: =IF(M95=0,"",E95/M95) | H95: =IF(N95=0,"",E95/N95) | I95: =IF(O95=0,"",E95/O95)
E96: =C96*D96 -> 0 | G96: =IF(M96=0,"",E96/M96) | H96: =IF(N96=0,"",E96/N96) | I96: =IF(O96=0,"",E96/O96)
E97: =C97*D97 -> 0 | G97: =IF(M97=0,"",E97/M97) | H97: =IF(N97=0,"",E97/N97) | I97: =IF(O97=0,"",E97/O97)
E98: =C98*D98 -> 0 | G98: =IF(M98=0,"",E98/M98) | H98: =IF(N98=0,"",E98/N98) | I98: =IF(O98=0,"",E98/O98)
E99: =C99*D99 -> 0 | G99: =IF(M99=0,"",E99/M99) | H99: =IF(N99=0,"",E99/N99) | I99: =IF(O99=0,"",E99/O99)
B100: TOTAL | E100: =SUM(E66:E99) -> 0 | G100: =IF(M100=0,"",E100/M100) | H100: =IF(N100=0,"",E100/N100) | I100: =IF(O100=0,"",E100/O100) | K100: =IF(G100="","",IF(I100>=1,$I$8,IF(H100>=1,$H$8,$G$8))) | M100: ='💰BUDGET PLAN💰'!E130 -> 0 | N100: ='💰BUDGET PLAN💰'!J130 -> 0 | O100: ='💰BUDGET PLAN💰'!O130 -> 0
B102: Divisi A | C102: P | D102: Q | E102: Total | G102: % Realization
E103: =C103*D103 -> 0 | G103: =IF(M103=0,"",E103/M103) | H103: =IF(N103=0,"",E103/N103) | I103: =IF(O103=0,"",E103/O103) | K103: =IF(G103="","",IF(I103>=1,$I$8,IF(H103>=1,$H$8,$G$8))) | M103: =SUMIF('💰BUDGET PLAN💰'!$B$133:$B$144,'💸BUDGET REALIZED💸'!B103,'💰BUDGET PLAN💰'!$E$133:$E$144) -> 0 | N103: =SUMIF('💰BUDGET PLAN💰'!$G$133:$G$144,'💸BUDGET REALIZED💸'!B103,'💰BUDGET PLAN💰'!$J$133:$J$144) -> 0 | O103: =SUMIF('💰BUDGET PLAN💰'!$L$133:$L$144,'💸BUDGET REALIZED💸'!B103,'💰BUDGET PLAN💰'!$O$133:$O$144) -> 0
E104: =C104*D104 -> 0 | G104: =IF(M104=0,"",E104/M104) | H104: =IF(N104=0,"",E104/N104) | I104: =IF(O104=0,"",E104/O104) | K104: =IF(G104="","",IF(I104>=1,$I$8,IF(H104>=1,$H$8,$G$8))) | M104: =SUMIF('💰BUDGET PLAN💰'!$B$133:$B$144,'💸BUDGET REALIZED💸'!B104,'💰BUDGET PLAN💰'!$E$133:$E$144) -> 0 | N104: =SUMIF('💰BUDGET PLAN💰'!$G$133:$G$144,'💸BUDGET REALIZED💸'!B104,'💰BUDGET PLAN💰'!$J$133:$J$144) -> 0 | O104: =SUMIF('💰BUDGET PLAN💰'!$L$133:$L$144,'💸BUDGET REALIZED💸'!B104,'💰BUDGET PLAN💰'!$O$133:$O$144) -> 0
E105: =C105*D105 -> 0 | G105: =IF(M105=0,"",E105/M105) | H105: =IF(N105=0,"",E105/N105) | I105: =IF(O105=0,"",E105/O105) | K105: =IF(G105="","",IF(I105>=1,$I$8,IF(H105>=1,$H$8,$G$8))) | M105: =SUMIF('💰BUDGET PLAN💰'!$B$133:$B$144,'💸BUDGET REALIZED💸'!B105,'💰BUDGET PLAN💰'!$E$133:$E$144) -> 0 | N105: =SUMIF('💰BUDGET PLAN💰'!$G$133:$G$144,'💸BUDGET REALIZED💸'!B105,'💰BUDGET PLAN💰'!$J$133:$J$144) -> 0 | O105: =SUMIF('💰BUDGET PLAN💰'!$L$133:$L$144,'💸BUDGET REALIZED💸'!B105,'💰BUDGET PLAN💰'!$O$133:$O$144) -> 0
E106: =C106*D106 -> 0 | G106: =IF(M106=0,"",E106/M106) | H106: =IF(N106=0,"",E106/N106) | I106: =IF(O106=0,"",E106/O106) | K106: =IF(G106="","",IF(I106>=1,$I$8,IF(H106>=1,$H$8,$G$8))) | M106: =SUMIF('💰BUDGET PLAN💰'!$B$133:$B$144,'💸BUDGET REALIZED💸'!B106,'💰BUDGET PLAN💰'!$E$133:$E$144) -> 0 | N106: =SUMIF('💰BUDGET PLAN💰'!$G$133:$G$144,'💸BUDGET REALIZED💸'!B106,'💰BUDGET PLAN💰'!$J$133:$J$144) -> 0 | O106: =SUMIF('💰BUDGET PLAN💰'!$L$133:$L$144,'💸BUDGET REALIZED💸'!B106,'💰BUDGET PLAN💰'!$O$133:$O$144) -> 0
E107: =C107*D107 -> 0 | G107: =IF(M107=0,"",E107/M107) | H107: =IF(N107=0,"",E107/N107) | I107: =IF(O107=0,"",E107/O107) | K107: =IF(G107="","",IF(I107>=1,$I$8,IF(H107>=1,$H$8,$G$8))) | M107: =SUMIF('💰BUDGET PLAN💰'!$B$133:$B$144,'💸BUDGET REALIZED💸'!B107,'💰BUDGET PLAN💰'!$E$133:$E$144) -> 0 | N107: =SUMIF('💰BUDGET PLAN💰'!$G$133:$G$144,'💸BUDGET REALIZED💸'!B107,'💰BUDGET PLAN💰'!$J$133:$J$144) -> 0 | O107: =SUMIF('💰BUDGET PLAN💰'!$L$133:$L$144,'💸BUDGET REALIZED💸'!B107,'💰BUDGET PLAN💰'!$O$133:$O$144) -> 0
E108: =C108*D108 -> 0 | G108: =IF(M108=0,"",E108/M108) | H108: =IF(N108=0,"",E108/N108) | I108: =IF(O108=0,"",E108/O108) | K108: =IF(G108="","",IF(I108>=1,$I$8,IF(H108>=1,$H$8,$G$8))) | M108: =SUMIF('💰BUDGET PLAN💰'!$B$133:$B$144,'💸BUDGET REALIZED💸'!B108,'💰BUDGET PLAN💰'!$E$133:$E$144) -> 0 | N108: =SUMIF('💰BUDGET PLAN💰'!$G$133:$G$144,'💸BUDGET REALIZED💸'!B108,'💰BUDGET PLAN💰'!$J$133:$J$144) -> 0 | O108: =SUMIF('💰BUDGET PLAN💰'!$L$133:$L$144,'💸BUDGET REALIZED💸'!B108,'💰BUDGET PLAN💰'!$O$133:$O$144) -> 0
...

Sheet 🚨CASHFLOW🚨
A1: ='TRACKING 💎MERCH💎'!A1 | I1: ⚠️ FILL IN THE COLOURLESS CELL ONLY⚠️ | R1: ⚠️ FILL IN THE COLOURLESS CELL ONLY⚠️ | AA1: ⚠️ FILL IN THE COLOURLESS CELL ONLY⚠️
I2: CASH FLOW | R2: 👑Cash Flow👑 | AA2: 👑Cash Flow👑
B3: Cash Growth | I3: Date | J3: Description | K3: Division | L3: Cash In | M3: Cash Out | N3: Transaction Proof (Attach the link and make it accessible) | O3: Cash Balance | P3: Ending Cash Balance | Q3: Q1 | R3: Date | S3: Description | T3: Division | U3: Cash In | V3: Cash Out | W3: Transaction Proof (Attach the link and make it accessible) | X3: Cash Balance | Y3: Ending Cash Balance | Z3: Q2 | AA3: Date | AB3: Description | AC3: Division | AD3: Cash In | AE3: Cash Out | AF3: Transaction Proof (Attach the link and make it accessible) | AG3: Cash Balance | AH3: Ending Cash Balance | AI3: Q3
B4: Period | D4: Total Cash In | E4: Total Cash Out | F4: Cash Balance | G4: % Growth | L4: =SUM(L6:L305) -> 130000 | M4: =SUM(M6:M305) -> 42000 | P4: =IF(SUM(L6:L1305)+SUM(M6:M1305)=0,0,SUM(L6:L1305)-SUM(M6:M1305)) -> 88000 | U4: =SUM(U6:U305) -> 0 | V4: =SUM(V6:V305) -> 0 | Y4: =IF(SUM(U6:U1305)+SUM(V6:V1305)=0,0,SUM(U6:U1305)-SUM(V6:V1305)) -> 0 | AD4: =SUM(AD6:AD305) -> 0 | AE4: =SUM(AE6:AE305) -> 0 | AH4: =IF(SUM(AD6:AD1305)+SUM(AE6:AE1305)=0,0,SUM(AD6:AD1305)-SUM(AE6:AE1305)) -> 0
F5: 24000000
B6: Q1 | D6: =sum(L6:L49) -> 130000 | E6: =sum(M6:M305) -> 42000 | F6: =IF(D6+E6=0," ",F5+D6-E6) -> 24088000 | G6: =(F6-F5)/F5 -> 0.0036666667 | I6: 46194 | J6: Beli bahan modal kain | L6: 100000 | O6: =IF(L6+M6=0," ",O4+L6-M6) -> 100000 | X6: =IF(U6+V6=0," ",X4+U6-V6) | AG6: =IF(AD6+AE6=0," ",AG4+AD6-AE6)
M7: 2000 | O7: =IF(L7+M7=0," ",O6+L7-M7) -> 98000 | P7: =P13 | X7: =IF(U7+V7=0," ",X6+U7-V7) | AG7: =IF(AD7+AE7=0," ",AG6+AD7-AE7)
L8: 30000 | O8: =IF(L8+M8=0," ",O7+L8-M8) -> 128000 | X8: =IF(U8+V8=0," ",X7+U8-V8) | AG8: =IF(AD8+AE8=0," ",AG7+AD8-AE8)
M9: 40000 | O9: =IF(L9+M9=0," ",O8+L9-M9) -> 88000 | X9: =IF(U9+V9=0," ",X8+U9-V9) | AG9: =IF(AD9+AE9=0," ",AG8+AD9-AE9)
B10: Q2 | D10: =sum(U4) -> 0 | E10: =sum(V4) -> 0 | F10: =IF(D10+E10=0," ",F5+D10-E10) | G10: =(F10-F5)/F5 -> #VALUE! | O10: =IF(L10+M10=0," ",O9+L10-M10) | X10: =IF(U10+V10=0," ",X9+U10-V10) | AG10: =IF(AD10+AE10=0," ",AG9+AD10-AE10)
O11: =IF(L11+M11=0," ",O10+L11-M11) | X11: =IF(U11+V11=0," ",X10+U11-V11) | AG11: =IF(AD11+AE11=0," ",AG10+AD11-AE11)
O12: =IF(L12+M12=0," ",O11+L12-M12) | X12: =IF(U12+V12=0," ",X11+U12-V12) | AG12: =IF(AD12+AE12=0," ",AG11+AD12-AE12)
O13: =IF(L13+M13=0," ",O12+L13-M13) | X13: =IF(U13+V13=0," ",X12+U13-V13) | AG13: =IF(AD13+AE13=0," ",AG12+AD13-AE13)
B14: Q3 | D14: =sum(L14:L57) -> 0 | E14: =sum(M14:M313) -> 0 | F14: =IF(D14+E14=0," ",F13+D14-E14) | G14: =(F14-F5)/F5 -> #VALUE! | O14: =IF(L14+M14=0," ",O13+L14-M14) | X14: =IF(U14+V14=0," ",X13+U14-V14) | AG14: =IF(AD14+AE14=0," ",AG13+AD14-AE14)
O15: =IF(L15+M15=0," ",O14+L15-M15) | X15: =IF(U15+V15=0," ",X14+U15-V15) | AG15: =IF(AD15+AE15=0," ",AG14+AD15-AE15)
O16: =IF(L16+M16=0," ",O15+L16-M16) | X16: =IF(U16+V16=0," ",X15+U16-V16) | AG16: =IF(AD16+AE16=0," ",AG15+AD16-AE16)
O17: =IF(L17+M17=0," ",O16+L17-M17) | X17: =IF(U17+V17=0," ",X16+U17-V17) | AG17: =IF(AD17+AE17=0," ",AG16+AD17-AE17)
B18: Q4 | D18: =sum(L18:L61) -> 0 | E18: =sum(M18:M317) -> 0 | F18: =IF(D18+E18=0," ",F17+D18-E18) | G18: =(F18-F5)/F5 -> #VALUE! | O18: =IF(L18+M18=0," ",O17+L18-M18) | X18: =IF(U18+V18=0," ",X17+U18-V18) | AG18: =IF(AD18+AE18=0," ",AG17+AD18-AE18)
O19: =IF(L19+M19=0," ",O18+L19-M19) | X19: =IF(U19+V19=0," ",X18+U19-V19) | AG19: =IF(AD19+AE19=0," ",AG18+AD19-AE19)
O20: =IF(L20+M20=0," ",O19+L20-M20) | X20: =IF(U20+V20=0," ",X19+U20-V20) | AG20: =IF(AD20+AE20=0," ",AG19+AD20-AE20)
O21: =IF(L21+M21=0," ",O20+L21-M21) | X21: =IF(U21+V21=0," ",X20+U21-V21) | AG21: =IF(AD21+AE21=0," ",AG20+AD21-AE21)
B22: Total | G22: =IFERROR(AVERAGE(G7:G21),0) -> 0 | O22: =IF(L22+M22=0," ",O21+L22-M22) | X22: =IF(U22+V22=0," ",X21+U22-V22) | AG22: =IF(AD22+AE22=0," ",AG21+AD22-AE22)
O23: =IF(L23+M23=0," ",O22+L23-M23) | X23: =IF(U23+V23=0," ",X22+U23-V23) | AG23: =IF(AD23+AE23=0," ",AG22+AD23-AE23)
O24: =IF(L24+M24=0," ",O23+L24-M24) | X24: =IF(U24+V24=0," ",X23+U24-V24) | AG24: =IF(AD24+AE24=0," ",AG23+AD24-AE24)
O25: =IF(L25+M25=0," ",O24+L25-M25) | X25: =IF(U25+V25=0," ",X24+U25-V25) | AG25: =IF(AD25+AE25=0," ",AG24+AD25-AE25)
O26: =IF(L26+M26=0," ",O25+L26-M26) | X26: =IF(U26+V26=0," ",X25+U26-V26) | AG26: =IF(AD26+AE26=0," ",AG25+AD26-AE26)
O27: =IF(L27+M27=0," ",O26+L27-M27) | X27: =IF(U27+V27=0," ",X26+U27-V27) | AG27: =IF(AD27+AE27=0," ",AG26+AD27-AE27)
O28: =IF(L28+M28=0," ",O27+L28-M28) | X28: =IF(U28+V28=0," ",X27+U28-V28) | AG28: =IF(AD28+AE28=0," ",AG27+AD28-AE28)
O29: =IF(L29+M29=0," ",O28+L29-M29) | X29: =IF(U29+V29=0," ",X28+U29-V29) | AG29: =IF(AD29+AE29=0," ",AG28+AD29-AE29)
O30: =IF(L30+M30=0," ",O29+L30-M30) | X30: =IF(U30+V30=0," ",X29+U30-V30) | AG30: =IF(AD30+AE30=0," ",AG29+AD30-AE30)
O31: =IF(L31+M31=0," ",O30+L31-M31) | X31: =IF(U31+V31=0," ",X30+U31-V31) | AG31: =IF(AD31+AE31=0," ",AG30+AD31-AE31)
O32: =IF(L32+M32=0," ",O31+L32-M32) | X32: =IF(U32+V32=0," ",X31+U32-V32) | AG32: =IF(AD32+AE32=0," ",AG31+AD32-AE32)
O33: =IF(L33+M33=0," ",O32+L33-M33) | X33: =IF(U33+V33=0," ",X32+U33-V33) | AG33: =IF(AD33+AE33=0," ",AG32+AD33-AE33)
O34: =IF(L34+M34=0," ",O33+L34-M34) | X34: =IF(U34+V34=0," ",X33+U34-V34) | AG34: =IF(AD34+AE34=0," ",AG33+AD34-AE34)
... O305: =IF(L305+M305=0," ",O304+L305-M305) | X305: =IF(U305+V305=0," ",X304+U305-V305) | AG305: =IF(AD305+AE305=0," ",AG304+AD305-AE305)

Sheet 💎MERCH💎
B1: Merchandising Detail
B2: Item | C2: P | D2: Q | E2: Total Gross | F2: COGS/Pcs | G2: Total COGS | H2: Net Profit
B3: Work Jacket | C3: 250000 | D3: 24 | E3: =C3*D3 -> 6000000 | G3: =F3*D3 -> 0 | H3: =E3-G3 -> 6000000
B4: Varsity | C4: 281000 | D4: 15 | E4: =C4*D4 -> 4215000 | G4: =F4*D4 -> 0 | H4: =E4-G4 -> 4215000
B5: Half Zip | C5: 225000 | D5: 15 | E5: =C5*D5 -> 3375000 | G5: =F5*D5 -> 0 | H5: =E5-G5 -> 3375000
B6: Kaos | C6: 85000 | D6: 30 | E6: =C6*D6 -> 2550000 | G6: =F6*D6 -> 0 | H6: =E6-G6 -> 2550000
B7: Topi | C7: 55000 | D7: 20 | E7: =C7*D7 -> 1100000 | G7: =F7*D7 -> 0 | H7: =E7-G7 -> 1100000
B8: Tumbler | C8: 75550 | D8: 20 | E8: =C8*D8 -> 1511000 | G8: =F8*D8 -> 0 | H8: =E8-G8 -> 1511000
B9: Totebag | C9: 50000 | D9: 40 | E9: =C9*D9 -> 2000000 | G9: =F9*D9 -> 0 | H9: =E9-G9 -> 2000000
B10: Keychain Biasa | C10: 20000 | D10: 140 | E10: =C10*D10 -> 2800000 | G10: =F10*D10 -> 0 | H10: =E10-G10 -> 2800000
B11: Keychain Clicker | C11: 50000 | D11: 10 | E11: =C11*D11 -> 500000 | G11: =F11*D11 -> 0 | H11: =E11-G11 -> 500000
B12: Sticker Pack | C12: 20000 | D12: 50 | E12: =C12*D12 -> 1000000 | G12: =F12*D12 -> 0 | H12: =E12-G12 -> 1000000
B13: Pin Tas 44 mm | C13: 3000 | D13: 100 | E13: =C13*D13 -> 300000 | G13: =F13*D13 -> 0 | H13: =E13-G13 -> 300000
B14: Pin Tas 58 mm | C14: 5000 | D14: 50 | E14: =C14*D14 -> 250000 | G14: =F14*D14 -> 0 | H14: =E14-G14 -> 250000
... B17: Bando Bara | C17: 15000 | D17: 50 | E17: =C17*D17 -> 750000 | G17: =F17*D17 -> 0 | H17: =E17-G17 -> 750000
B18: Pulpen | E18: =C18*D18 -> 0 | G18: =F18*D18 -> 0 | H18: =E18-G18 -> 0
B19: Pensil | E19: =C19*D19 -> 0 | G19: =F19*D19 -> 0 | H19: =E19-G19 -> 0
B20: Buku | E20: =C20*D20 -> 0 | G20: =F20*D20 -> 0 | H20: =E20-G20 -> 0
D21: =SUM(D2:D11) -> 314 | E21: =SUM(E3:E20) -> 35851000 | G21: =SUM(G3:G20) -> 0 | H21: =SUM(H3:H20) -> 35851000

Sheet TRACKING 💎MERCH💎
B1: 💎Merchandising Detail💎
B2: Item | C2: P | D2: Q | E2: Total Gross | F2: COGS/Pcs | G2: Total COGS | H2: Net Profit
B3: Work Jacket | C3: 250000 | D3: 24 | E3: =C3*D3 -> 6000000 | F3: 65000 | G3: =F3*D3 -> 1560000 | H3: =E3-G3 -> 4440000
B4: Varsity | C4: 281000 | D4: 15 | E4: =C4*D4 -> 4215000 | G4: =F4*D4 -> 0 | H4: =E4-G4 -> 4215000
B5: Half Zip | C5: 225000 | D5: 15 | E5: =C5*D5 -> 3375000 | G5: =F5*D5 -> 0 | H5: =E5-G5 -> 3375000
B6: Kaos | C6: 85000 | D6: 30 | E6: =C6*D6 -> 2550000 | G6: =F6*D6 -> 0 | H6: =E6-G6 -> 2550000
B7: Topi | C7: 55000 | D7: 20 | E7: =C7*D7 -> 1100000 | G7: =F7*D7 -> 0 | H7: =E7-G7 -> 1100000
B8: Tumbler | C8: 75550 | D8: 20 | E8: =C8*D8 -> 1511000 | G8: =F8*D8 -> 0 | H8: =E8-G8 -> 1511000
B9: Totebag | C9: 50000 | D9: 40 | E9: =C9*D9 -> 2000000 | G9: =F9*D9 -> 0 | H9: =E9-G9 -> 2000000
B10: Keychain Biasa | C10: 20000 | D10: 140 | E10: =C10*D10 -> 2800000 | G10: =F10*D10 -> 0 | H10: =E10-G10 -> 2800000
B11: Keychain Clicker | C11: 50000 | D11: 10 | E11: =C11*D11 -> 500000 | G11: =F11*D11 -> 0 | H11: =E11-G11 -> 500000
B12: Sticker Pack | C12: 20000 | D12: 50 | E12: =C12*D12 -> 1000000 | G12: =F12*D12 -> 0 | H12: =E12-G12 -> 1000000
B13: Pin Tas 44 mm | C13: 3000 | D13: 100 | E13: =C13*D13 -> 300000 | G13: =F13*D13 -> 0 | H13: =E13-G13 -> 300000
B14: Pin Tas 58 mm | C14: 5000 | D14: 50 | E14: =C14*D14 -> 250000 | G14: =F14*D14 -> 0 | H14: =E14-G14 -> 250000
B15: Pin Enamel | C15: 30000 | D15: 150 | E15: =C15*D15 -> 4500000 | G15: =F15*D15 -> 0 | H15: =E15-G15 -> 4500000
... B17: Bando Bara | C17: 15000 | D17: 50 | E17: =C17*D17 -> 750000 | G17: =F17*D17 -> 0 | H17: =E17-G17 -> 750000
B18: Pulpen | E18: =C18*D18 -> 0 | G18: =F18*D18 -> 0 | H18: =E18-G18 -> 0
B19: Pensil | E19: =C19*D19 -> 0 | G19: =F19*D19 -> 0 | H19: =E19-G19 -> 0
B20: Buku | E20: =C20*D20 -> 0 | G20: =F20*D20 -> 0 | H20: =E20-G20 -> 0
D21: =SUM(D3:D20) -> 814 | E21: =SUM(E3:E20) -> 35851000 | G21: =SUM(G3:G20) -> 1560000 | H21: =SUM(H3:H20) -> 34291000
B23: Total Quantity Based on Pre Order | F23: Ready stock to sell on-site
B24: Item | C24: Q | D24: Total | F24: Item | G24: Q | H24: Expected Profit
B25: Test | C25: =D3+D10 -> 164 | D25: =C25 -> 164
C26: =D4+D10 -> 155 | D26: =C26 -> 155
C27: =D5+D10+D11+D12 -> 215 | D27: =C27*4 -> 860
C28: =D6+D10+D11+D13 -> 280 | D28: =C28 -> 280
C29: =D7+D10+D11+D12+D13 -> 320 | D29: =ROUNDUP(C29/9+2,0) -> 38 | G29: =SUM(G25:G28) -> 0 | H29: =SUM(H25:H28) -> 0
C30: =D8+D14+D20 -> 70 | D30: =ROUNDUP(C30/9,0) + (5) -> 13
C31: =D9+D14+D20 -> 90 | D31: =C31 -> 90
C32: =#REF!+D14 -> #REF! | D32: =C32 -> #REF!
C33: =SUM(C24:C32) -> #REF! | D33: =SUM(D24:D32) -> #REF!
B35: 💎Production Costs💎
B36: Item | C36: Raw Materials Costs | D36: Detailed Quantity | E36: Q | F36: Total Q | G36: Direct Labor Costs | H36: COGS/Pcs | I36: Total COGS
B37: Work Jacket | D37: 1 | F37: =(D37*E37) -> 0 | G37: 0 | I37: =C37*E37+G37 -> 0
B38: Varsity | C38: 120000 | D38: 1 | E38: 20 | F38: =(D38*E38) -> 20 | G38: 30000 | H38: =I38/F38 -> 121500 | I38: =C38*E38+G38 -> 2430000
B39: Half Zip | D39: 1 | F39: =(D39*E39) -> 0 | G39: 0 | H39: =I39/F39 -> #DIV/0! | I39: =C39*E39+G39 -> 0
B40: Kaos | D40: 1 | E40: x | F40: =(D40*E40) -> #VALUE! | G40: 0 | H40: =I40/F40 -> #VALUE! | I40: =C40*E40+G40 -> #VALUE!
B41: Topi | D41: 1 | F41: =(D41*E41) -> 0 | G41: 0 | H41: =I41/F41 -> #DIV/0! | I41: =C41*E41+G41 -> 0
B42: Tumbler | D42: 1 | F42: =(D42*E42) -> 0 | G42: 0 | H42: =I42/F42 -> #DIV/0! | I42: =C42*E42+G42 -> 0
B43: Totebag | D43: 1 | F43: =(D43*E43) -> 0 | G43: 0 | H43: =I43/F43 -> #DIV/0! | I43: =C43*E43+G43 -> 0
B44: Keychain Biasa | D44: 1 | F44: =(D44*E44) -> 0 | G44: - | H44: =I44/F44 -> #VALUE! | I44: =C44*E44+G44 -> #VALUE!
B45: Keychain Clicker | D45: 1 | F45: =(D45*E45) -> 0 | G45: 0 | H45: =I45/F45 -> #DIV/0! | I45: =C45*E45+G45 -> 0
B46: Sticker Packs | D46: 1 | F46: =(D46*E46) -> 0 | G46: 0 | H46: =I46/F46 -> #DIV/0! | I46: =C46*E46+G46 -> 0
B47: Pin Tas 44 mm | D47: 1 | F47: =(D47*E47) -> 0 | G47: 0 | H47: =I47/F47 -> #DIV/0! | I47: =C47*E47+G47 -> 0
B48: Pin Tas 58 mm | D48: 1 | F48: =(D48*E48) -> 0 | G48: 0 | H48: =I48/F48 -> #DIV/0! | I48: =C48*E48+G48 -> 0
B49: Pin Enamel | D49: 1 | F49: =(D49*E49) -> 0 | G49: 0 | H49: =I49/F49 -> #DIV/0! | I49: =C49*E49+G49 -> 0
B50: Boneka Bara | D50: 1 | F50: =(D50*E50) -> 0 | G50: 0 | H50: =I50/F50 -> #DIV/0! | I50: =C50*E50+G50 -> 0
B51: Bando Bara | D51: 1 | F51: =(D51*E51) -> 0 | G51: 0 | H51: =I51/F51 -> #DIV/0! | I51: =C51*E51+G51 -> 0
B52: Pensil | D52: 1 | F52: =(D52*E52) -> 0 | G52: 0 | H52: =I52/F52 -> #DIV/0! | I52: =C52*E52+G52 -> 0
B53: Pulpen | D53: 1 | F53: =(D53*E53) -> 0 | G53: 0 | H53: =I53/F53 -> #DIV/0! | I53: =C53*E53+G53 -> 0
B54: Buku | D54: 1 | F54: =(D54*E54) -> 0 | G54: 0 | H54: =I54/F54 -> #DIV/0! | I54: =C54*E54+G54 -> 0
F55: =(D55*E55) -> 0 | G55: 0 | H55: =I55/F55 -> #DIV/0! | I55: =C55*E55+G55 -> 0
E56: =SUM(E37:E40,E42:E55) -> 20 | F56: =SUM(F37:F55) -> #VALUE! | G56: =SUM(G37:G55) -> 30000 | I56: =SUM(I37:I55) -> #VALUE!

Sheet Reimbursement
B1: Reimbursement Tracker
I3: =SUMIF($J$7:$J$597, "paid", $I$7:$I$597) -> 0 | J3: =COUNTIF($J$7:$J$597, "paid") -> 0
I4: =SUMIF($J$7:$J$597, "unpaid", I7:I597) -> 0 | J4: =COUNTIF($J$7:$J$597, "unpaid") -> 0
B6: Expense Proof | C6: Request Date | D6: Name | E6: Description | F6: Source | G6: Category | H6: Date Paid | I6: Amount of Money | J6: Status | K6: Proof link

Sheet READY STOCK MERCH
B1: 💎Merchandising Detail💎
B2: Item | C2: P | D2: Q | E2: Total Gross | F2: COGS/Pcs | G2: Total COGS | H2: Net Profit
E3: =C3*D3 -> 0 | G3: =F3*D3 -> 0 | H3: =E3-G3 -> 0
E4: =C4*D4 -> 0 | G4: =F4*D4 -> 0 | H4: =E4-G4 -> 0
E5: =C5*D5 -> 0 | G5: =F5*D5 -> 0 | H5: =E5-G5 -> 0
E6: =C6*D6 -> 0 | G6: =F6*D6 -> 0 | H6: =E6-G6 -> 0
E7: =C7*D7 -> 0 | G7: =F7*D7 -> 0 | H7: =E7-G7 -> 0
E8: =C8*D8 -> 0 | G8: =F8*D8 -> 0 | H8: =E8-G8 -> 0
D9: =SUM(D2:D8) -> 0 | E9: =SUM(E3:E8) -> 0 | G9: =SUM(G3:G8) -> 0 | H9: =SUM(H3:H8) -> 0

Sheet Sheet9
A1: Item ID | B1: Item name | C1: Type | D1: Initial Stock | E1: Stock In | F1: Sold (Qris Payment) | G1: Sold (Cash Payment) | H1: Remaining Stock | I1: Total Sold | J1: Unit Price | K1: Cost Price | L1: Revenue | M1: Profit | N1: Status | O1: Notes
A2: 1 | B2: Work Jacket | D2: 20 | F2: 6 | G2: 5 | H2: =(D2+E2) -(F2+G2) -> 9 | I2: =F2+G2 -> 11 | N2: In stock
A3: 2 | F3: 8 | H3: =(D3+E3) -(F3+G3) -> -8 | I3: =F3+G3 -> 8 | J3: 200000 | K3: 150000 | N3: Sold out
A4: 3 | E4: 68 | F4: 121 | H4: =(D4+E4) -(F4+G4) -> -53 | I4: =F4+G4 -> 121 | N4: In stock
A5: 4 | F5: 52 | H5: =(D5+E5) -(F5+G5) -> -52 | I5: =F5+G5 -> 52 | N5: In stock
A6: 5 | H6: =(D6+E6) -(F6+G6) -> 0 | I6: =F6+G6 -> 0 | N6: In stock
A7: 6 | F7: 3 | H7: =(D7+E7) -(F7+G7) -> -3 | I7: =F7+G7 -> 3 | N7: In stock
A8: 7 | F8: 4 | H8: =(D8+E8) -(F8+G8) -> -4 | I8: =F8+G8 -> 4 | N8: In stock
A9: 8 | F9: 2 | H9: =(D9+E9) -(F9+G9) -> -2 | I9: =F9+G9 -> 2 | N9: In stock
A10: 9 | F10: 7 | H10: =(D10+E10) -(F10+G10) -> -7 | I10: =F10+G10 -> 7 | N10: In stock
A11: 10 | F11: 35 | G11: 1 | H11: =(D11+E11) -(F11+G11) -> -36 | I11: =F11+G11 -> 36 | N11: In stock
A12: 11 | F12: 27 | G12: 5 | H12: =(D12+E12) -(F12+G12) -> -32 | I12: =F12+G12 -> 32 | N12: Re-purchase needed
A13: 12 | F13: 15 | H13: =(D13+E13) -(F13+G13) -> -15 | I13: =F13+G13 -> 15 | N13: In stock
A14: 13 | F14: 7 | H14: =(D14+E14) -(F14+G14) -> -7 | I14: =F14+G14 -> 7 | N14: In stock
A15: 14 | F15: 21 | H15: =(D15+E15) -(F15+G15) -> -21 | I15: =F15+G15 -> 21 | N15: Re-purchase needed
A16: 15 | F16: 6 | H16: =(D16+E16) -(F16+G16) -> -6 | I16: =F16+G16 -> 6 | N16: Sold out
A17: 16 | F17: 4 | H17: =(D17+E17) -(F17+G17) -> -4 | I17: =F17+G17 -> 4 | N17: In stock
A18: 17 | H18: =(D18+E18) -(F18+G18) -> 0 | I18: =F18+G18 -> 0
A19: 18 | H19: =(D19+E19) -(F19+G19) -> 0 | I19: =F19+G19 -> 0
A20: 19 | H20: =(D20+E20) -(F20+G20) -> 0 | I20: =F20+G20 -> 0
A21: 20 | H21: =(D21+E21) -(F21+G21) -> 0 | I21: =F21+G21 -> 0
A22: 21 | H22: =(D22+E22) -(F22+G22) -> 0 | I22: =F22+G22 -> 0
A23: 22 | H23: =(D23+E23) -(F23+G23) -> 0 | I23: =F23+G23 -> 0
A24: 23 | H24: =(D24+E24) -(F24+G24) -> 0 | I24: =F24+G24 -> 0
A25: 24 | H25: =(D25+E25) -(F25+G25) -> 0 | I25: =F25+G25 -> 0
A26: 25 | H26: =(D26+E26) -(F26+G26) -> 0 | I26: =F26+G26 -> 0
A27: 26 | H27: =(D27+E27) -(F27+G27) -> 0 | I27: =F27+G27 -> 0
A28: 27 | H28: =(D28+E28) -(F28+G28) -> 0 | I28: =F28+G28 -> 0
